Workbook

Sheet ESG Structure
B2: Full ESG Index | E2: Environment | I2: Social | M2: Composite
B3: Company | C3: Ticker | D3: Sector | E3: Climate Targets | F3: Investment & Transition | G3: Climate Reporting | H3: Environment Score | I3: DEI Targets & Representation | J3: DEI Programmes & Memberships | K3: Social Incentives | L3: Social Score | M3: Total Scores
B4: 3i | C4: III | D4: Financial services | E4: ='Environment '!G109 -> 0.6875 | F4: ='Environment '!L109 -> 0 | G4: ='Environment '!Q109 -> 0.2 | H4: ='Environment '!R109 -> 0.29583333 | I4: =Social!G110 -> 0.625 | J4: =Social!K110 -> 0.33333333 | K4: =Social!O110 -> 0.66666667 | L4: =Social!P110 -> 0.54166667 | M4: =(FullIndex[[#This Row],[Environment Score]]+FullIndex[[#This Row],[Social Score]])/2 -> 0.41875
B5: Admiral Group | C5: ADM | D5: Insurance | E5: ='Environment '!G110 -> 0.6875 | F5: ='Environment '!L110 -> 0.1875 | G5: ='Environment '!Q110 -> 0.3825 | H5: ='Environment '!R110 -> 0.41916667 | I5: =Social!G111 -> 0.525 | J5: =Social!K111 -> 0 | K5: =Social!O111 -> 0.83333333 | L5: =Social!P111 -> 0.45277778 | M5: =(FullIndex[[#This Row],[Environment Score]]+FullIndex[[#This Row],[Social Score]])/2 -> 0.43597222
B6: Airtel Africa | C6: AAF | D6: Telecommunications services | E6: ='Environment '!G111 -> 0.125 | F6: ='Environment '!L111 -> 0.0625 | G6: ='Environment '!Q111 -> 0.125 | H6: ='Environment '!R111 -> 0.10416667 | I6: =Social!G112 -> 0.3625 | J6: =Social!K112 -> 0 | K6: =Social!O112 -> 0.33333333 | L6: =Social!P112 -> 0.23194444 | M6: =(FullIndex[[#This Row],[Environment Score]]+FullIndex[[#This Row],[Social Score]])/2 -> 0.16805556
B7: Alliance Witan | C7: ALW | D7: Investment Trusts | E7: ='Environment '!G112 -> 0.25 | F7: ='Environment '!L112 -> 0 | G7: ='Environment '!Q112 -> 0.01 | H7: ='Environment '!R112 -> 0.086666667 | I7: =Social!G113 -> 0.25 | J7: =Social!K113 -> 0 | K7: =Social!O113 -> 0.5 | L7: =Social!P113 -> 0.25 | M7: =(FullIndex[[#This Row],[Environment Score]]+FullIndex[[#This Row],[Social Score]])/2 -> 0.16833333
B8: Anglo American | C8: AAL | D8: Mining | E8: ='Environment '!G113 -> 0.5125 | F8: ='Environment '!L113 -> 0.375 | G8: ='Environment '!Q113 -> 0.86 | H8: ='Environment '!R113 -> 0.5825 | I8: =Social!G114 -> 0.625 | J8: =Social!K114 -> 0.33333333 | K8: =Social!O114 -> 0.5 | L8: =Social!P114 -> 0.48611111 | M8: =(FullIndex[[#This Row],[Environment Score]]+FullIndex[[#This Row],[Social Score]])/2 -> 0.53430556
B9: Antofagasta | C9: ANTO | D9: Mining | E9: ='Environment '!G114 -> 0.65 | F9: ='Environment '!L114 -> 0.4375 | G9: ='Environment '!Q114 -> 0.5225 | H9: ='Environment '!R114 -> 0.53666667 | I9: =Social!G115 -> 0.4625 | J9: =Social!K115 -> 0 | K9: =Social!O115 -> 0.33333333 | L9: =Social!P115 -> 0.26527778 | M9: =(FullIndex[[#This Row],[Environment Score]]+FullIndex[[#This Row],[Social Score]])/2 -> 0.40097222
B10: Ashtead Group | C10: AHT | D10: Support services | E10: ='Environment '!G115 -> 0.4 | F10: ='Environment '!L115 -> 0 | G10: ='Environment '!Q115 -> 0.15 | H10: ='Environment '!R115 -> 0.18333333 | I10: =Social!G116 -> 0.425 | J10: =Social!K116 -> 0 | K10: =Social!O116 -> 0.5 | L10: =Social!P116 -> 0.30833333 | M10: =(FullIndex[[#This Row],[Environment Score]]+FullIndex[[#This Row],[Social Score]])/2 -> 0.24583333
B11: Associated British Foods | C11: ABF | D11: Food & tobacco | E11: ='Environment '!G116 -> 0.625 | F11: ='Environment '!L116 -> 0.5 | G11: ='Environment '!Q116 -> 0.5925 | H11: ='Environment '!R116 -> 0.5725 | I11: =Social!G117 -> 0.65 | J11: =Social!K117 -> 0.33333333 | K11: =Social!O117 -> 0.33333333 | L11: =Social!P117 -> 0.43888889 | M11: =(FullIndex[[#This Row],[Environment Score]]+FullIndex[[#This Row],[Social Score]])/2 -> 0.50569444
B12: AstraZeneca | C12: AZN | D12: Pharmaceuticals & biotechnology | E12: ='Environment '!G117 -> 1 | F12: ='Environment '!L117 -> 0.75 | G12: ='Environment '!Q117 -> 0.475 | H12: ='Environment '!R117 -> 0.74166667 | I12: =Social!G118 -> 0.5875 | J12: =Social!K118 -> 1 | K12: =Social!O118 -> 0.66666667 | L12: =Social!P118 -> 0.75138889 | M12: =(FullIndex[[#This Row],[Environment Score]]+FullIndex[[#This Row],[Social Score]])/2 -> 0.74652778
B13: Auto Trader Group | C13: AUTO | D13: Media | E13: ='Environment '!G118 -> 0.4375 | F13: ='Environment '!L118 -> 0 | G13: ='Environment '!Q118 -> 0.32 | H13: ='Environment '!R118 -> 0.2525 | I13: =Social!G119 -> 0.6875 | J13: =Social!K119 -> 0 | K13: =Social!O119 -> 1 | L13: =Social!P119 -> 0.5625 | M13: =(FullIndex[[#This Row],[Environment Score]]+FullIndex[[#This Row],[Social Score]])/2 -> 0.4075
B14: Aviva | C14: AV | D14: Life insurance | E14: ='Environment '!G119 -> 0.6875 | F14: ='Environment '!L119 -> 0.375 | G14: ='Environment '!Q119 -> 0.2275 | H14: ='Environment '!R119 -> 0.43 | I14: =Social!G120 -> 0.625 | J14: =Social!K120 -> 0 | K14: =Social!O120 -> 1 | L14: =Social!P120 -> 0.54166667 | M14: =(FullIndex[[#This Row],[Environment Score]]+FullIndex[[#This Row],[Social Score]])/2 -> 0.48583333
B15: Babcock International Group | C15: BAB | D15: Aerospace & defence | E15: ='Environment '!G120 -> 0.375 | F15: ='Environment '!L120 -> 0.1875 | G15: ='Environment '!Q120 -> 0.205 | H15: ='Environment '!R120 -> 0.25583333 | I15: =Social!G121 -> 0.625 | J15: =Social!K121 -> 0 | K15: =Social!O121 -> 0.5 | L15: =Social!P121 -> 0.375 | M15: =(FullIndex[[#This Row],[Environment Score]]+FullIndex[[#This Row],[Social Score]])/2 -> 0.31541667
... B103: WPP | C103: WPP | D103: Media | E103: ='Environment '!G208 -> 0.6875 | F103: ='Environment '!L208 -> 0.1875 | G103: ='Environment '!Q208 -> 0.3775 | H103: ='Environment '!R208 -> 0.4175 | I103: =Social!G209 -> 0.625 | J103: =Social!K209 -> 0.33333333 | K103: =Social!O209 -> 0.66666667 | L103: =Social!P209 -> 0.54166667 | M103: =(FullIndex[[#This Row],[Environment Score]]+FullIndex[[#This Row],[Social Score]])/2 -> 0.47958333

Sheet Environment 
B2: Social Raw Data (Weight: 40%) | U2: Environment
B3: Domains: | C3: E1 | H3: E2 | M3: E3 | U3: E1 - Climate Targets | V3: E2 - Investment and Transition Actions | W3: E3 - Climate Reporting
B4: Company | C4: Net Zero Commitment | D4: Scope Coverage | E4: SBTi Validation | F4: TPI Alignment | H4: Decarb/CapEx | I4: Green Bonds ($bn) | J4: Memberships | K4: Internal Carbon Price | M4: Sust. Report Page # | N4: CDP Score | O4: Climate KPI's | P4: Assurance Level
B5: 3i | C5: 2040 | D5: 1+2+3 | E5: Yes | F5: N/A | H5: None | I5: N/A | J5: No | K5: No | M5: 30 | N5: N/A | O5: N/A | P5: Limited | U5: 1. Net Zero Commitment Year | V5: 1. Decarbonisation Capex | W5: 1. Sustainability Report Page Number
B6: Admiral Group | C6: 2040 | D6: 1+2+3 | E6: Yes | F6: N/A | H6: None | I6: 0.75 | J6: No | K6: No | M6: 43 | N6: B | O6: N/A | P6: Limited | U6: Earlier = stronger commitment = higher inverted score. | V6: No action (None) = 0 | W6: Total Page Numbers
B7: Airtel Africa | C7: 2050 | D7: Unclear | E7: No | F7: N/A | H7: None | I7: 0.3 | J7: No | K7: No | M7: 50 | N7: N/A | O7: N/A | P7: None | U7: Example scoring: | V7: a) Plans to phase out carbon intensive Capex = 0.5 | W7: Score = (# disclosed ÷ 11)
B8: Alliance Witan | C8: 2050 | D8: 1+2 | E8: No | F8: N/A | H8: None | I8: N/A | J8: No | K8: No | M8: 4 | N8: N/A | O8: N/A | P8: None | U8: ≤ 2030 → 1.0 | V8: b) Has decarb. Investments/spend = 0.75
B9: Anglo American | C9: 2040 | D9: 1+2 | E9: No | F9: 4 | H9: None | I9: 0.74 | J9: No | K9: Yes | M9: 144 | N9: N/A | O9: Yes | P9: Reasonable | U9: 2031–2040 → 0.75 | V9: c) Has both a & b = 1 | W9: 2. CDP Score - https://knowesg.com/
B10: Antofagasta | C10: 2050 | D10: 1+2 | E10: Yes | F10: 3 | H10: B | I10: N/A | J10: No | K10: Yes | M10: 99 | N10: B | O10: No | P10: Limited | U10: 2041–2050 → 0.5 | W10: Map A/A- = 1 → B = 0.7 → C = 0.4 → D = 0.2 → F = 0
B11: Ashtead Group | C11: 2050 | D11: 1+2 | E11: No | F11: 3 | H11: None | I11: N/A | J11: No | K11: No | M11: N/A | N11: B | O11: No | P11: None | U11: > 2050 / no year → 0.2 | V11: 2. Green Bonds
B12: Associated British Foods | C12: 2050 | D12: 1+2+3 | E12: No | F12: 5 | H12: C | I12: N/A | J12: No | K12: Yes | M12: 27 | N12: B | O12: Yes | P12: Limited | U12: No commitment → 0 | V12: Issued > £1bn = 1 | W12: 3. Climate KPIs in Executive Pay
B13: AstraZeneca | C13: 2025 | D13: 1+2+3 | E13: Yes | F13: 5 | H13: C | I13: N/A | J13: Gold | K13: Yes | M13: 40 | N13: N/A | O13: Yes | P13: Limited | V13: £100m–1bn = 0.5 | W13: Binary:
B14: Auto Trader Group | C14: 2040 | D14: 1+2+3 | E14: No | F14: N/A | H14: None | I14: N/A | J14: No | K14: No | M14: 18 | N14: B | O14: N/A | P14: Limited | U14: 2. Scope Coverage | V14: <£100m = 0.25 | W14: Yes = 1
B15: Aviva | C15: 2040 | D15: 1+2+3 | E15: Yes | F15: N/A | H15: B | I15: N/A | J15: Yes | K15: No | M15: 11 | N15: A- | O15: N/A | P15: None | U15: Scopes 1+2+3 → 1 | V15: None = 0 | W15: No = 0
B16: Babcock International Group | C16: 2050 | D16: 1+2+3 | E16: No | F16: N/A | H16: B | I16: N/A | J16: No | K16: No | M16: 32 | N16: N/A | O16: N/A | P16: Limited | U16: Scopes 1+2 only → 0.5
B17: BAE Systems | C17: 2030 | D17: 1+2+3 | E17: Yes | F17: 4 | H17: None | I17: N/A | J17: No | K17: No | M17: 6 | N17: N/A | O17: Yes | P17: Limited | U17: Scope 1 only → 0.25 | V17: 3. RE100/EP100/EV100 Membership | W17: 4. Assurance Level
B18: Barclays | C18: 2050 | D18: 1+2+3 | E18: No | F18: 5 | H18: C | I18: 1.14 | J18: Gold | K18: Yes | M18: 41 | N18: A- | O18: Yes | P18: Limited | U18: None → 0 | V18: Binary: | W18: Reasonable = 1
B19: Barratt Developments | C19: 2040 | D19: Unclear | E19: Yes | F19: N/A | H19: None | I19: N/A | J19: No | K19: No | M19: N/A | N19: A | O19: N/A | P19: Limited | V19: Yes = 1, If Gold = 1.2 | W19: Limited = 0.5
B20: Beazley | C20: 2050 | D20: 1+2 | E20: No | F20: N/A | H20: None | I20: N/A | J20: No | K20: No | M20: 26 | N20: N/A | O20: N/A | P20: None | U20: 3. SBTi Validation | V20: No = 0 | W20: None = 0
B21: Berkeley Group Holdings | C21: 2450 | D21: 1+2+3 | E21: No | F21: N/A | H21: None | I21: 0.55 | J21: No | K21: No | M21: 30 | N21: N/A | O21: N/A | P21: Limited | U21: 1.5°C → 1
B22: BP | C22: 2050 | D22: 1+2+3 | E22: Yes | F22: 5 | H22: C | I22: N/A | J22: No | K22: Yes | M22: 49 | N22: N/A | O22: Yes | P22: None | U22: WB2°C → 0.75 | V22: 4. Internal Carbon Price Reported
B23: British American Tobacco | C23: 2050 | D23: 1+2+3 | E23: Yes | F23: 3 | H23: A | I23: N/A | J23: No | K23: Yes | M23: 104 | N23: A | O23: No | P23: None | U23: 2°C → 0.5 | V23: Binary:
B24: British Land | C24: 2030 | D24: 1+2 | E24: No | F24: N/A | H24: None | I24: N/A | J24: Yes | K24: No | M24: 27 | N24: N/A | O24: N/A | P24: None | U24: Commit only → 0.25 | V24: Yes = 1
B25: BT Group | C25: 2041 | D25: 1+2+3 | E25: Yes | F25: 5 | H25: C | I25: N/A | J25: Yes | K25: Yes | M25: 23 | N25: A | O25: Yes | P25: Reasonable | U25: No SBTi → 0 | V25: No = 0
B26: Bunzl | C26: 2050 | D26: 1+2+3 | E26: Yes | F26: 3 | H26: None | I26: N/A | J26: No | K26: No | M26: 26 | N26: N/A | O26: No | P26: Limited
B27: Burberry Group | C27: 2040 | D27: 1+2+3 | E27: Yes | F27: N/A | H27: None | I27: N/A | J27: Gold | K27: No | M27: 28 | N27: A- | O27: N/A | P27: None | U27: 4. TPI Alignment
B28: Centrica | C28: 2040 | D28: 1+2+3 | E28: Yes | F28: 5 | H28: C | I28: N/A | J28: No | K28: Yes | M28: 46 | N28: B | O28: Yes | P28: Limited | U28: TPI gives 0–4 or 0–5 level scores; normalize by dividing by max.
B29: Coca-Cola HBC | C29: 2040 | D29: 1+2+3 | E29: Yes | F29: 5 | H29: C | I29: N/A | J29: Yes | K29: Yes | M29: 14 | N29: A | O29: Yes | P29: Limited
B30: Compass Group | C30: 2050 | D30: 1+2+3 | E30: Yes | F30: 3 | H30: None | I30: 1.65 | J30: No | K30: No | M30: 42 | N30: N/A | O30: No | P30: Limited
B31: Convatec Group | C31: 2045 | D31: 1+2+3 | E31: No | F31: N/A | H31: None | I31: N/A | J31: No | K31: No | M31: N/A | N31: B | O31: N/A | P31: Limited
B32: Croda International | C32: 2050 | D32: 1+2+3 | E32: No | F32: 3 | H32: None | I32: N/A | J32: No | K32: Yes | M32: 25 | N32: A- | O32: No | P32: Limited
B33: DCC plc | C33: 2050 | D33: 1+2 | E33: Yes | F33: 3 | H33: None | I33: N/A | J33: No | K33: No | M33: 41 | N33: A | O33: No | P33: Limited
B34: Diageo | C34: 2050 | D34: 1+2+3 | E34: Yes | F34: 4 | H34: None | I34: N/A | J34: Yes | K34: No | M34: 71 | N34: N/A | O34: Yes | P34: Limited
B35: Diploma | C35: 2045 | D35: 1+2+3 | E35: No | F35: N/A | H35: None | I35: N/A | J35: No | K35: No | M35: 4 | N35: C | O35: N/A | P35: None
B36: Endeavour Mining | C36: 2050 | D36: 1+2 | E36: No | F36: 3 | H36: None | I36: N/A | J36: No | K36: Yes | M36: 98 | N36: B | O36: No | P36: Limited
B37: Entain | C37: 2035 | D37: 1+2+3 | E37: No | F37: N/A | H37: None | I37: N/A | J37: No | K37: No | M37: 42 | N37: B | O37: N/A | P37: Limited
B38: EasyJet | C38: 2050 | D38: 1+2+3 | E38: No | F38: 5 | H38: C | I38: N/A | J38: No | K38: Yes | M38: 5 | N38: N/A | O38: Yes | P38: Reasonable
B39: Experian | C39: 2050 | D39: Unclear | E39: Yes | F39: N/A | H39: None | I39: N/A | J39: No | K39: No | M39: 28 | N39: A- | O39: N/A | P39: Limited
B40: F&C Investment Trust | C40: 2050 | D40: Unclear | E40: No | F40: N/A | H40: None | I40: N/A | J40: No | K40: No | M40: N/A | N40: N/A | O40: N/A | P40: None
B41: Fresnillo | C41: 2030 | D41: Unclear | E41: No | F41: N/A | H41: None | I41: N/A | J41: No | K41: No | M41: 2 | N41: C | O41: N/A | P41: Limited
B42: Games Workshop | C42: 2050 | D42: Unclear | E42: No | F42: N/A | H42: None | I42: N/A | J42: No | K42: No | M42: 1 | N42: N/A | O42: N/A | P42: None
B43: Glencore | C43: 2050 | D43: 1+2+3 | E43: No | F43: 4 | H43: B | I43: N/A | J43: No | K43: No | M43: 70 | N43: N/A | O43: Yes | P43: Limited
B44: GSK | C44: 2045 | D44: 1+2+3 | E44: No | F44: 5 | H44: C | I44: N/A | J44: No | K44: Yes | M44: 54 | N44: A | O44: Yes | P44: Limited
B45: Haleon | C45: 2040 | D45: 1+2+3 | E45: No | F45: 3 | H45: B | I45: N/A | J45: No | K45: Yes | M45: 76 | N45: B | O45: Yes | P45: Limited
B46: Halma | C46: 2040 | D46: 1+2+3 | E46: No | F46: N/A | H46: None | I46: N/A | J46: No | K46: No | M46: 33 | N46: B | O46: N/A | P46: Limited
B47: Hargreaves Lansdown | C47: 2050 | D47: 1+2+3 | E47: No | F47: N/A | H47: None | I47: N/A | J47: No | K47: No | M47: 1 | N47: N/A | O47: N/A | P47: None
B48: Hikma Pharmaceuticals | C48: 2030 | D48: Unclear | E48: No | F48: N/A | H48: None | I48: N/A | J48: No | K48: No | M48: 53 | N48: B | O48: N/A | P48: Limited
B49: Hiscox | C49: 2050 | D49: Unclear | E49: No | F49: N/A | H49: None | I49: N/A | J49: No | K49: No | M49: 1 | N49: B | O49: N/A | P49: None
B50: Howden Joinery Group | C50: 2050 | D50: 1+2+3 | E50: No | F50: N/A | H50: None | I50: N/A | J50: No | K50: No | M50: 10 | N50: B | O50: N/A | P50: None
B51: HSBC Holdings | C51: 2050 | D51: 1+2 | E51: No | F51: 3 | H51: C | I51: 0.19 | J51: Yes | K51: No | M51: 31 | N51: N/A | O51: Yes | P51: Limited
B52: IMI plc | C52: 2040 | D52: 1+2+3 | E52: No | F52: N/A | H52: None | I52: N/A | J52: No | K52: No | M52: 1 | N52: B | O52: N/A | P52: None
B53: Imperial Brands | C53: 2050 | D53: 1+2+3 | E53: No | F53: 3 | H53: None | I53: N/A | J53: No | K53: Yes | M53: 38 | N53: A | O53: Yes | P53: Limited
B54: Informa | C54: 2050 | D54: Unclear | E54: Yes | F54: N/A | H54: None | I54: N/A | J54: No | K54: No | M54: 56 | N54: N/A | O54: N/A | P54: Limited
B55: Intercontinental Hotels Group | C55: 2050 | D55: 1+2+3 | E55: Yes | F55: 4 | H55: None | I55: N/A | J55: No | K55: No | M55: 65 | N55: N/A | O55: Yes | P55: None
B56: Intermediate Capital Group | C56: 2050 | D56: Unclear | E56: No | F56: N/A | H56: None | I56: 0.56 | J56: No | K56: No | M56: 69 | N56: A- | O56: N/A | P56: Limited
B57: Intertek Group | C57: 2050 | D57: 1+2 | E57: Yes | F57: 3 | H57: None | I57: N/A | J57: No | K57: No | M57: 136 | N57: A- | O57: Yes | P57: Limited
B58: International Cons. Airlines (IAG) | C58: 2050 | D58: 1+2+3 | E58: No | F58: N/A | H58: B | I58: 0.55 | J58: No | K58: No | M58: 80 | N58: N/A | O58: N/A | P58: None
B59: JD Sports Fashion | C59: 2050 | D59: 1+2 | E59: No | F59: 3 | H59: None | I59: N/A | J59: Yes | K59: No | M59: 1 | N59: A | O59: No
B60: Kingfisher | C60: 2050 | D60: 1+2+3 | E60: Yes | F60: 4 | H60: B | I60: N/A | J60: No | K60: No | M60: 49 | N60: A | O60: Yes
B61: Land Securities (Landsec) | C61: 2050 | D61: 1+2+3 | E61: Yes | F61: N/A | H61: None | I61: N/A | J61: Yes | K61: No | M61: 58 | N61: N/A | O61: N/A | P61: Limited
B62: Legal & General | C62: 2050 | D62: Unclear | E62: No | F62: N/A | H62: B | I62: N/A | J62: No | K62: No | M62: 73 | N62: A | O62: N/A | P62: None
B63: Lloyds Banking Group | C63: 2050 | D63: 1+2+3 | E63: Yes | F63: 4 | H63: C | I63: 4.35 | J63: Yes | K63: No | M63: 145 | N63: A- | O63: Yes | P63: Limited
B64: LondonMetric Property | C64: 2050 | D64: 1+2+3 | E64: No | F64: N/A | H64: None | I64: 0.67 | J64: No | K64: No | M64: 40 | N64: A- | O64: N/A | P64: Limited
B65: London Stock Exchange Group | C65: 2050 | D65: 1+2+3 | E65: Yes | F65: 5 | H65: C | I65: N/A | J65: Yes | K65: Yes | M65: 59 | N65: A- | O65: Yes | P65: Limited
B66: M&G | C66: 2050 | D66: Unclear | E66: No | F66: N/A | H66: None | I66: N/A | J66: Yes | K66: No | M66: 33 | N66: C | O66: N/A | P66: Limited
B67: Marks & Spencer | C67: 2040 | D67: 1+2+3 | E67: Yes | F67: 3 | H67: None | I67: N/A | J67: No | K67: Yes | M67: 59 | N67: B | O67: No | P67: Limited
B68: Melrose Industries | C68: 2050 | D68: 1+2+3 | E68: No | F68: 3 | H68: None | I68: N/A | J68: No | K68: No | M68: 86 | N68: B | O68: Yes | P68: None
B69: Mondi | C69: 2050 | D69: 1+2+3 | E69: Yes | F69: 5 | H69: C | I69: N/A | J69: No | K69: Yes | M69: 109 | N69: A- | O69: Yes | P69: Limited
B70: National Grid | C70: 2050 | D70: 1+2+3 | E70: Yes | F70: 5 | H70: C | I70: 1.02 | J70: No | K70: Yes | M70: 8 | N70: A- | O70: Yes | P70: Limited
B71: NatWest Group | C71: 2050 | D71: 1+2+3 | E71: No | F71: N/A | H71: B | I71: =2.62+4.25 -> 6.87 | J71: Yes | K71: No | M71: 99 | N71: A | O71: N/A | P71: None
B72: Next plc | C72: 2050 | D72: Unclear | E72: Yes | F72: N/A | H72: None | I72: N/A | J72: Yes | K72: No | M72: 58 | N72: N/A | O72: N/A | P72: None
B73: Pearson | C73: 2030 | D73: 1+2+3 | E73: Yes | F73: N/A | H73: None | I73: 0.9 | J73: Yes | K73: No | M73: 16 | N73: A- | O73: N/A | P73: Limited
B74: Persimmon | C74: 2050 | D74: 1+2+3 | E74: Yes | F74: N/A | H74: None | I74: N/A | J74: No | K74: No | M74: 200 | N74: A- | O74: N/A | P74: Limited
B75: Phoenix Group | C75: 2050 | D75: Unclear | E75: No | F75: N/A | H75: None | I75: N/A | J75: No | K75: No | M75: 5 | N75: N/A | O75: N/A | P75: Limited
B76: Prudential | C76: 2050 | D76: 1+2+3 | E76: Yes | F76: 4 | H76: None | I76: N/A | J76: No | K76: No | M76: 87 | N76: A- | O76: Yes | P76: Limited
B77: Reckitt Benckiser | C77: 2050 | D77: 1+2+3 | E77: No | F77: 3 | H77: None | I77: N/A | J77: Yes | K77: Yes | M77: 68 | N77: A | O77: No | P77: Limited
B78: RELX | C78: 2050 | D78: 1+2+3 | E78: Yes | F78: 3 | H78: None | I78: N/A | J78: Yes | K78: Yes | M78: 37 | N78: B | O78: No | P78: Limited
B79: Rentokil Initial | C79: 2050 | D79: 1+2 | E79: No | F79: 3 | H79: None | I79: N/A | J79: No | K79: No | M79: 76 | N79: N/A | O79: No | P79: None
B80: Rightmove | C80: 2050 | D80: 1+2+3 | E80: No | F80: N/A | H80: None | I80: N/A | J80: No | K80: No | M80: 19 | N80: N/A | O80: N/A | P80: None
B81: Rio Tinto | C81: 2030 | D81: 1+2+3 | E81: Yes | F81: 5 | H81: C | I81: N/A | J81: No | K81: Yes | M81: 14 | N81: N/A | O81: No | P81: Limited
B82: Rolls-Royce Holdings | C82: 2050 | D82: 1+2+3 | E82: Yes | F82: 4 | H82: B | I82: N/A | J82: No | K82: No | M82: 1 | N82: C | O82: Yes | P82: Limited
B83: Sage Group | C83: 2040 | D83: 1+2+3 | E83: No | F83: N/A | H83: None | I83: =0.29+0.38 -> 0.67 | J83: No | K83: No | M83: 36 | N83: A | O83: N/A | P83: Limited
B84: Sainsbury’s | C84: 2035 | D84: 1+2+3 | E84: Yes | F84: 5 | H84: C | I84: N/A | J84: No | K84: Yes | M84: 40 | N84: A | O84: Yes | P84: Limited
B85: Schroders | C85: 2050 | D85: Unclear | E85: Yes | F85: N/A | H85: C | I85: N/A | J85: Yes | K85: No | M85: 72 | N85: A | O85: N/A | P85: None
B86: Scottish Mortgage Trust | C86: 2050 | D86: 1+2+3 | E86: No | F86: N/A | H86: None | I86: N/A | J86: No | K86: No | M86: 14 | N86: N/A | O86: N/A | P86: None
B87: Segro | C87: 2030 | D87: 1+2+3 | E87: No | F87: N/A | H87: None | I87: N/A | J87: No | K87: No | M87: 73 | N87: A | O87: N/A | P87: Limited
B88: Severn Trent | C88: 2050 | D88: 1+2+3 | E88: Yes | F88: 3 | H88: None | I88: =2.93+3.05 -> 5.98 | J88: No | K88: Yes | M88: 23 | N88: A | O88: Yes | P88: None
B89: Shell plc | C89: 2050 | D89: 1+2+3 | E89: Yes | F89: 5 | H89: C | I89: N/A | J89: No | K89: Yes | M89: 98 | N89: N/A | O89: Yes | P89: Limited
B90: Smith & Nephew | C90: 2045 | D90: 1+2+3 | E90: Yes | F90: 3 | H90: None | I90: N/A | J90: No | K90: No | M90: 49 | N90: B | O90: No | P90: None
B91: Smiths Group | C91: 2040 | D91: 1+2+3 | E91: Yes | F91: N/A | H91: None | I91: N/A | J91: No | K91: No | M91: 28 | N91: B | O91: N/A | P91: Limited
B92: Spirax-Sarco (Spirax Group) | C92: 2050 | D92: 1+2+3 | E92: No | F92: N/A | H92: None | I92: N/A | J92: No | K92: No | M92: 22 | N92: A | O92: N/A | P92: Limited
B93: SSE plc | C93: 2050 | D93: 1+2+3 | E93: No | F93: 5 | H93: C | I93: 2.88 | J93: No | K93: Yes | M93: 49 | N93: N/A | O93: Yes | P93: Limited
B94: St. James’s Place | C94: 2050 | D94: Unclear | E94: No | F94: N/A | H94: None | I94: N/A | J94: No | K94: No | M94: 52 | N94: C | O94: N/A | P94: None
B95: Standard Chartered | C95: 2050 | D95: 1+2+3 | E95: No | F95: N/A | H95: B | I95: =0.08+1.09+0.46+1.19 -> 2.82 | J95: Yes | K95: No | M95: 38 | N95: A | O95: N/A | P95: Limited
B96: Taylor Wimpey | C96: 2045 | D96: 1+2+3 | E96: No | F96: N/A | H96: None | I96: N/A | J96: No | K96: No | M96: 58 | N96: A | O96: N/A | P96: Limited
B97: Tesco | C97: 2050 | D97: 1+2+3 | E97: Yes | F97: 5 | H97: C | I97: 1.46 | J97: Yes | K97: Yes | M97: 61 | N97: A- | O97: Yes | P97: Limited
B98: Unilever | C98: 2050 | D98: 1+2+3 | E98: Yes | F98: 5 | H98: C | I98: N/A | J98: Gold | K98: Yes | M98: 69 | N98: N/A | O98: Yes | P98: Reasonable
B99: Unite Group (United Group) | C99: 2030 | D99: 1+2 | E99: No | F99: N/A | H99: None | I99: N/A | J99: No | K99: No | M99: 128 | N99: A | O99: N/A | P99: Limited
B100: United Utilities Group | C100: 2030 | D100: 1+2+3 | E100: Yes | F100: 5 | H100: C | I100: N/A | J100: No | K100: Yes | M100: 47 | N100: N/A | O100: Yes | P100: Limited
B101: Vodafone Group | C101: 2040 | D101: 1+2+3 | E101: Yes | F101: 5 | H101: C | I101: 0.84 | J101: Yes | K101: Yes | M101: 49 | N101: A | O101: Yes | P101: Limited
...

Sheet Social
B2: Social Raw Data (Weight: 40%) | R2: Social
B3: Domains: | C3: S1 | H3: S2 | L3: S3 | R3: S1 - DEI Targets & Representation | S3: S2 - Programmes & Memberships | T3: S3 - Social Governance & Incentives
B4: Company | C4: Gender Target | D4: Leadership Gender % | E4: Ethnicity Target | F4: Workforce Representation | H4: Stonewall/10000 | I4: Bloomberg | J4: Wdi Rep | L4: Diversity Linked to Exec Pay | M4: Board DEI Oversight | N4: Senior Management Target
B5: 3i | C5: Formal | D5: 0.4 | E5: Formal | H5: 1 | I5: No | J5: No | L5: Linked | M5: Yes | N5: No | R5: 1. Gender/Ethnicity Targets | S5: 1. DEI Memberships | T5: 1. Diversity Linked to Exec Pay
B6: Admiral Group | C6: Formal | D6: 0.455 | E6: Aspirational | H6: None | I6: No | J6: No | L6: Partially Linked | M6: Yes | N6: Yes | R6: Use your existing classification: | S6: Binary (0 or 1) for each: | T6: Linked = 1
B7: Airtel Africa | C7: Aspirational | D7: 0.333 | E7: Aspirational | H7: None | I7: No | J7: No | L7: Not Linked | M7: Yes | N7: No | S7: Stonewall | T7: Partially Linked = 0.5
B8: Alliance Witan | C8: N/A | D8: 0 | E8: Formal | H8: None | I8: No | J8: No | L8: Partially Linked | M8: Yes | N8: No | R8: Formal numeric target → 1 | S8: 10,000 Black Interns | T8: Not Linke = 0
B9: Anglo American | C9: Formal | D9: 0.455 | E9: Formal | H9: None | I9: Yes | J9: No | L9: Partially Linked | M9: Yes | N9: No | R9: Aspirational target → 0.6 | S9: Race at Work Charter
B10: Antofagasta | C10: Formal | D10: 0.308 | E10: Aspirational | H10: None | I10: No | J10: No | L10: Not Linked | M10: Yes | N10: No | R10: Metric only (“monitoring”) → 0.3 | S10: Any other DEI coalition | T10: 2. Board Oversight
B11: Ashtead Group | C11: Formal | D11: 0.222 | E11: Aspirational | H11: None | I11: No | J11: No | L11: Partially Linked | M11: Yes | N11: No | R11: No target → 0 | T11: Dedicated DEI/People Committee = 1
B12: Associated British Foods | C12: Formal | D12: 0.6 | E12: Aspirational | H12: None | I12: No | J12: Yes | L12: Not Linked | M12: Yes | N12: No | S12: Normalize by dividing by total possible memberships. | T12: Some oversight = 0.5
B13: AstraZeneca | C13: Formal | D13: 0.5 | E13: Aspirational | H13: 1 | I13: Yes | J13: Yes | L13: Linked | M13: Yes | N13: No | R13: 2. Representation thresholds | T13: None = 0
B14: Auto Trader Group | C14: Formal | D14: 0.556 | E14: Formal | H14: None | I14: No | J14: No | L14: Linked | M14: Yes | N14: Yes | R14: Gender at board/exec/workforce: | S14: 2. Internal DEI Programmes
B15: Aviva | C15: Formal | D15: 0.462 | E15: Formal | H15: None | I15: No | J15: No | L15: Linked | M15: Yes | N15: Yes | R15: ≥50% women → 1 | S15: Exec‑level DEI officer = 1 | T15: 3. Committed to Senior Management Target?
B16: Babcock International Group | C16: Formal | D16: 0.4 | E16: Formal | H16: None | I16: No | J16: No | L16: Partially Linked | M16: Yes | N16: No | R16: ≥40% → 0.75 | S16: ERGs, formal training programs = +0.25 each (cap at 1) | T16: Yes/No
B17: BAE Systems | C17: Formal | D17: 0.417 | E17: Aspirational | H17: None | I17: Yes | J17: No | L17: Linked | M17: Yes | N17: No | R17: ≥30% → 0.5
B18: Barclays | C18: Formal | D18: 0.462 | E18: Formal | H18: 1 | I18: No | J18: No | L18: Linked | M18: Yes | N18: Yes | R18: <30% → 0.25
B19: Barratt Developments | C19: Formal | D19: 0.5 | E19: Aspirational | H19: None | I19: No | J19: No | L19: Not Linked | M19: Yes | N19: Yes
B20: Beazley | C20: Formal | D20: 0.455 | E20: Formal | H20: None | I20: No | J20: No | L20: Linked | M20: Yes | N20: Yes | R20: Workforce Representation
B21: Berkeley Group Holdings | C21: Formal | D21: 0.444 | E21: Aspirational | H21: None | I21: No | J21: No | L21: Not Linked | M21: Yes | N21: Yes | R21: ≥15% exec = 1
B22: BP | C22: Formal | D22: 0.385 | E22: Aspirational | H22: None | I22: No | J22: No | L22: Linked | M22: Yes | N22: No | R22: ≥10% = 0.75
B23: British American Tobacco | C23: Formal | D23: 0.5 | E23: Formal | H23: None | I23: Yes | J23: Yes | L23: Linked | M23: Yes | N23: No | R23: ≥5% = 0.5
B24: British Land | C24: Formal | D24: 0.5 | E24: Formal | H24: 1 | I24: No | J24: No | L24: Partially Linked | M24: Yes | N24: Yes | R24: <5% = 0.25
B25: BT Group | C25: Aspirational | D25: 0.357 | E25: Formal | H25: None | I25: No | J25: No | L25: Partially Linked | M25: Yes | N25: Yes
B26: Bunzl | C26: Formal | D26: 0.556 | E26: Aspirational | H26: None | I26: No | J26: No | L26: Not Linked | M26: Yes | N26: No | R26: 3. Target Deadline Strength
B27: Burberry Group | C27: Formal | D27: 0.556 | E27: Formal | H27: 1 | I27: Yes | J27: Yes | L27: Linked | M27: Yes | N27: Yes | R27: 2025 or earlier → 1
B28: Centrica | C28: Formal | D28: 0.462 | E28: Formal | H28: None | I28: No | J28: Yes | L28: Partially Linked | M28: Yes | N28: Yes | R28: 2030 → 0.5
B29: Coca-Cola HBC | C29: Formal | D29: 0.278 | E29: Aspirational | H29: None | I29: Yes | J29: No | L29: Partially Linked | M29: Yes | N29: No | R29: No deadline → 0
B30: Compass Group | C30: Formal | D30: 0.417 | E30: Formal | H30: None | I30: No | J30: No | L30: Partially Linked | M30: Yes | N30: Yes
B31: Convatec Group | C31: Formal | D31: 0.556 | E31: Aspirational | H31: None | I31: No | J31: Yes | L31: Partially Linked | M31: Yes | N31: No
B32: Croda International | C32: Formal | D32: 0.333 | E32: Aspirational | H32: None | I32: No | J32: No | L32: Partially Linked | M32: Yes | N32: Yes
B33: DCC plc | C33: Formal | D33: 0.364 | E33: Aspirational | H33: None | I33: No | J33: No | L33: Not Linked | M33: Yes | N33: No
B34: Diageo | C34: Formal | D34: 0.778 | E34: Formal | H34: None | I34: Yes | J34: No | L34: Linked | M34: Yes | N34: No
B35: Diploma | C35: Aspirational | D35: 0.444 | E35: Aspirational | H35: None | I35: No | J35: No | L35: Not Linked | M35: Yes | N35: Yes
B36: Endeavour Mining | C36: Aspirational | D36: 0.4 | E36: Aspirational | H36: None | I36: No | J36: No | L36: Not Linked | M36: Yes | N36: Yes
B37: Entain | C37: Formal | D37: 0.364 | E37: Aspirational | H37: None | I37: No | J37: No | L37: Partially Linked | M37: Yes | N37: Yes
B38: EasyJet | C38: Formal | D38: 0.4 | E38: Formal | H38: None | I38: No | J38: No | L38: Partially Linked | M38: Yes | N38: No
B39: Experian | C39: Formal | D39: 0.444 | E39: Formal | H39: None | I39: No | J39: No | L39: Linked | M39: Yes | N39: No
B40: F&C Investment Trust | C40: Formal | D40: 0 | E40: Formal | H40: None | I40: No | J40: No | L40: Partially Linked | M40: Yes | N40: No
B41: Fresnillo | C41: Aspirational | D41: 0.385 | E41: Aspirational | H41: None | I41: No | J41: Yes | L41: Not Linked | M41: Yes | N41: No
... B43: Glencore | C43: Formal | D43: 0.444 | E43: Aspirational | H43: None | I43: No | J43: No | L43: Partially Linked | M43: Yes | N43: No
B44: GSK | C44: Formal | D44: 0.5 | E44: Aspirational | H44: 1 | I44: No | J44: Yes | L44: Linked | M44: Yes | N44: No
B45: Haleon | C45: Formal | D45: 0.583 | E45: Aspirational | H45: None | I45: No | J45: No | L45: Linked | M45: Yes | N45: Yes
B46: Halma | C46: Formal | D46: 0.544 | E46: Formal | H46: None | I46: No | J46: No | L46: Partially Linked | M46: Yes | N46: Yes
B47: Hargreaves Lansdown | C47: Formal | D47: 0 | E47: Formal | H47: None | I47: No | J47: Yes | L47: Partially Linked | M47: Yes | N47: No
B48: Hikma Pharmaceuticals | C48: Formal | D48: 0.455 | E48: Aspirational | H48: None | I48: No | J48: No | L48: Not Linked | M48: Yes | N48: No
B49: Hiscox | C49: Formal | D49: 0.5 | E49: Formal | H49: None | I49: No | J49: No | L49: Linked | M49: Yes | N49: Yes
B50: Howden Joinery Group | C50: Formal | D50: 0.556 | E50: Aspirational | H50: None | I50: No | J50: No | L50: Not Linked | M50: Yes | N50: No
B51: HSBC Holdings | C51: Aspirational | D51: 0.615 | E51: Formal | H51: 1 | I51: Yes | J51: Yes | L51: Partially Linked | M51: Yes | N51: No
B52: IMI plc | C52: Formal | D52: 0.444 | E52: Aspirational | H52: None | I52: No | J52: No | L52: Not Linked | M52: Yes | N52: Yes
B53: Imperial Brands | C53: Formal | D53: 0.364 | E53: Aspirational | H53: None | I53: No | J53: Yes | L53: Partially Linked | M53: Yes | N53: Yes
B54: Informa | C54: Formal | D54: 0.455 | E54: Aspirational | H54: None | I54: No | J54: No | L54: Partially Linked | M54: Yes | N54: Yes
B55: Intercontinental Hotels Group | C55: Formal | D55: 0.4 | E55: Formal | H55: None | I55: No | J55: Yes | L55: Linked | M55: Yes | N55: No
B56: Intermediate Capital Group | C56: Formal | D56: 0 | E56: Formal | H56: None | I56: No | J56: No | L56: Linked | M56: Yes | N56: Yes
B57: Intertek Group | C57: Formal | D57: 0.308 | E57: Aspirational | H57: None | I57: No | J57: No | L57: Not Linked | M57: Yes | N57: No
B58: International Cons. Airlines (IAG) | C58: Formal | D58: 0.5 | E58: Formal | H58: None | I58: No | J58: No | L58: Partially Linked | M58: Yes | N58: No
B59: JD Sports Fashion | C59: Aspirational | D59: 0.3 | E59: Aspirational | H59: 1 | I59: No | J59: No | L59: Not Linked | M59: Yes | N59: Yes
B60: Kingfisher | C60: Formal | D60: 0.375 | E60: Aspirational | H60: 1 | I60: No | J60: Yes | L60: Partially Linked | M60: Yes | N60: Yes
B61: Land Securities | C61: Formal | D61: 0.455 | E61: Formal | H61: None | I61: No | J61: No | L61: Linked | M61: Yes | N61: Yes
B62: Legal & General | C62: Formal | D62: 0.417 | E62: Formal | H62: None | I62: Yes | J62: No | L62: Linked | M62: Yes | N62: Yes
B63: Lloyds Banking Group | C63: Formal | D63: 0.5 | E63: Formal | H63: 1 | I63: Yes | J63: No | L63: Linked | M63: Yes | N63: Yes
B64: LondonMetric Property | C64: Formal | D64: 0.444 | E64: Formal | H64: None | I64: No | J64: No | L64: Partially Linked | M64: Yes | N64: Yes
B65: London Stock Exchange Group | C65: Formal | D65: 0.333 | E65: Formal | H65: None | I65: No | J65: No | L65: Linked | M65: Yes | N65: Yes
B66: M&G | C66: Formal | D66: 0.4 | E66: Formal | H66: None | I66: Yes | J66: No | L66: Partially Linked | M66: Yes | N66: No
B67: Marks & Spencer | C67: Formal | D67: 0.667 | E67: Aspirational | H67: None | I67: No | J67: Yes | L67: Not Linked | M67: Yes | N67: Yes
B68: Melrose Industries | C68: Aspirational | D68: 0.4 | E68: Aspirational | H68: None | I68: No | J68: No | L68: Not Linked | M68: Yes | N68: Yes
B69: Mondi | C69: Formal | D69: 0.4 | E69: Aspirational | H69: None | I69: No | J69: No | L69: Partially Linked | M69: Yes | N69: No
B70: National Grid | C70: Formal | D70: 0.417 | E70: Formal | H70: None | I70: Yes | J70: Yes | L70: Linked | M70: Yes | N70: No
B71: NatWest Group | C71: Formal | D71: 0.6 | E71: Formal | H71: 2 | I71: Yes | J71: No | L71: Partially Linked | M71: Yes | N71: No
B72: Next plc | C72: Metric Only | D72: 0.333 | E72: Metric Only | H72: 1 | I72: No | J72: No | L72: Not Linked | M72: Yes | N72: No
B73: Pearson | C73: Formal | D73: 0.633 | E73: Formal | H73: None | I73: Yes | J73: No | L73: Linked | M73: Yes | N73: Yes
B74: Persimmon | C74: Formal | D74: 0.444 | E74: Aspirational | H74: None | I74: No | J74: No | L74: Not Linked | M74: Yes | N74: Yes
B75: Phoenix Group | C75: Formal | D75: 0.583 | E75: Formal | H75: None | I75: No | J75: No | L75: Linked | M75: Yes | N75: Yes
B76: Prudential | C76: Formal | D76: 0.333 | E76: Aspirational | H76: None | I76: Yes | J76: Yes | L76: Not Linked | M76: Yes | N76: No
B77: Reckitt Benckiser | C77: Formal | D77: 0.583 | E77: Aspirational | H77: None | I77: No | J77: No | L77: Linked | M77: Yes | N77: No
B78: RELX | C78: Formal | D78: 0.4 | E78: Aspirational | H78: None | I78: Yes | J78: No | L78: Linked | M78: Yes | N78: No
B79: Rentokil Initial | C79: Formal | D79: 0.364 | E79: Aspirational | H79: None | I79: No | J79: No | L79: Partially Linked | M79: Yes | N79: No
B80: Rightmove | C80: Formal | D80: 0.5 | E80: Formal | H80: None | I80: No | J80: No | L80: Partially Linked | M80: Yes | N80: No
B81: Rio Tinto | C81: Aspirational | D81: 0.4 | E81: Aspirational | H81: None | I81: No | J81: Yes | L81: Partially Linked | M81: Yes | N81: Yes
B82: Rolls-Royce Holdings | C82: Formal | D82: 0.5 | E82: Aspirational | H82: None | I82: No | J82: No | L82: Partially Linked | M82: Yes | N82: No
B83: Sage Group | C83: Formal | D83: 0.4 | E83: Formal | H83: None | I83: No | J83: No | L83: Linked | M83: Yes | N83: No
B84: Sainsbury’s | C84: Formal | D84: 0.5 | E84: Formal | H84: None | I84: No | J84: Yes | L84: Partially Linked | M84: Yes | N84: Yes
... B91: Smiths Group | C91: Formal | D91: 0.273 | E91: Aspirational | H91: None | I91: No | J91: No | L91: Not Linked | M91: Yes | N91: Yes
B92: Spirax-Sarco (Spirax Group) | C92: Formal | D92: 0.5 | E92: Aspirational | H92: 1 | I92: No | J92: No | L92: Not Linked | M92: Yes | N92: Yes
B93: SSE plc | C93: Formal | D93: 0.455 | E93: Formal | H93: None | I93: Yes | J93: Yes | L93: Linked | M93: Yes | N93: Yes
B94: St. James’s Place | C94: Formal | D94: 0.444 | E94: Formal | H94: 1 | I94: No | J94: No | L94: Partially Linked | M94: Yes | N94: Yes
B95: Standard Chartered | C95: Formal | D95: 0.455 | E95: Aspirational | H95: 1 | I95: Yes | J95: No | L95: Not Linked | M95: Yes | N95: Yes
B96: Taylor Wimpey | C96: Formal | D96: 0 | E96: Aspirational | H96: None | I96: No | J96: No | L96: Not Linked | M96: Yes | N96: No
B97: Tesco | C97: Formal | D97: 0.364 | E97: Aspirational | H97: 1 | I97: No | J97: Yes | L97: Partially Linked | M97: Yes | N97: No
B98: Unilever | C98: Formal | D98: 0.4 | E98: Formal | H98: 1 | I98: Yes | J98: No | L98: Linked | M98: Yes | N98: No
B99: Unite Group (United Group) | C99: Aspirational | D99: 0 | E99: Aspirational | H99: 1 | I99: No | J99: No | L99: Not Linked | M99: Yes | N99: Yes
B100: United Utilities Group | C100: Formal | D100: 0.455 | E100: Formal | H100: None | I100: Yes | J100: Yes | L100: Partially Linked | M100: Yes | N100: Yes
B101: Vodafone Group | C101: Formal | D101: 0.462 | E101: Aspirational | H101: None | I101: Yes | J101: Yes | L101: Not Linked | M101: Yes | N101: No
B102: Weir Group | C102: Formal | D102: 0.444 | E102: Aspirational | H102: None | I102: No | J102: No | L102: Partially Linked | M102: Yes | N102: No
B103: Whitbread | C103: Formal | D103: 0.5 | E103: Formal | H103: None | I103: No | J103: No | L103: Linked | M103: Yes | N103: Yes
B104: WPP | C104: Formal | D104: 0.455 | E104: Formal | H104: None | I104: Yes | J104: No | L104: Linked | M104: Yes | N104: No
B105: Sources | D105: https://ftsewomenleaders.com/company-rankings/ | E105: https://parkerreview.co.uk/wp-content/uploads/2026/03/The-Parker-Review-March-2026.pdf | J105: https://wdi.trust.org/wdi-awards-2024/
B107: Social Scores (Weight: 40%)
B108: Domains: | C108: S1 | H108: S2 | L108: S3
B109: Company | C109: Board Gender | D109: Leadership Gender % | E109: Ethnicity Target | F109: Workforce Representation | G109: S1 Score | H109: Stonewall/10000 | I109: Bloomberg | J109: WDI Rep | K109: S2 Score | L109: Diversity Linked to Exec Pay | M109: Board DEI Oversight | N109: Senior Management Target | O109: S3 Score | P109: Social Score
...

Sheet Governance
B2: Governance Raw Data - Embedded in E and S and coppied here | N2: Governance Treatment
B3: Domains: | C3: G1 | H3: G2
B4: Company | C4: Sust. Report Page # | D4: CDP Score | E4: Climate KPI's | F4: Assurance Level | H4: Diversity Linked to Exec Pay | I4: Board DEI Oversight | J4: Senior Management Target | N4: Governance-related indicators are treated as embedded within the live Environment and Social frameworks rather than presented as a
B5: 3i | C5: 30 | D5: N/A | E5: N/A | F5: Limited | H5: Linked | I5: Yes | J5: No | N5: standalone score. In the underlying methodology, governance appears through strategy, oversight, incentives, transparency, and
B6: Admiral Group | C6: 43 | D6: B | E6: N/A | F6: Limited | H6: Partially Linked | I6: Yes | J6: Yes | N6: assurance-related signals. These include ESG integration into corporate strategy and risk management, board-level oversight structures,
B7: Airtel Africa | C7: 50 | D7: N/A | E7: N/A | F7: None | H7: Not Linked | I7: Yes | J7: No | N7: diversity-linked incentives, formal committees, external frameworks, and third-party assurance.
B8: Alliance Witan | C8: 4 | D8: N/A | E8: N/A | F8: None | H8: Partially Linked | I8: Yes | J8: No
B9: Anglo American | C9: 144 | D9: N/A | E9: Yes | F9: Reasonable | H9: Partially Linked | I9: Yes | J9: No | N9: For the website, those governance signals are reflected primarily through the reporting, oversight, and incentive-related measures already
B10: Antofagasta | C10: 99 | D10: B | E10: No | F10: Limited | H10: Not Linked | I10: Yes | J10: No | N10: captured inside the Environment and Social domains. This keeps governance visible in the logic of the index without displaying it as a separate
B11: Ashtead Group | C11: N/A | D11: B | E11: No | F11: None | H11: Partially Linked | I11: Yes | J11: No | N11: scored pillar.
B12: Associated British Foods | C12: 27 | D12: B | E12: Yes | F12: Limited | H12: Not Linked | I12: Yes | J12: No
B13: AstraZeneca | C13: 40 | D13: N/A | E13: Yes | F13: Limited | H13: Linked | I13: Yes | J13: No
B14: Auto Trader Group | C14: 18 | D14: B | E14: N/A | F14: Limited | H14: Linked | I14: Yes | J14: Yes
B15: Aviva | C15: 11 | D15: A- | E15: N/A | F15: None | H15: Linked | I15: Yes | J15: Yes
B16: Babcock International Group | C16: 32 | D16: N/A | E16: N/A | F16: Limited | H16: Partially Linked | I16: Yes | J16: No
B17: BAE Systems | C17: 6 | D17: N/A | E17: Yes | F17: Limited | H17: Linked | I17: Yes | J17: No
B18: Barclays | C18: 41 | D18: A- | E18: Yes | F18: Limited | H18: Linked | I18: Yes | J18: Yes
B19: Barratt Developments | C19: N/A | D19: A | E19: N/A | F19: Limited | H19: Not Linked | I19: Yes | J19: Yes
B20: Beazley | C20: 26 | D20: N/A | E20: N/A | F20: None | H20: Linked | I20: Yes | J20: Yes
B21: Berkeley Group Holdings | C21: 30 | D21: N/A | E21: N/A | F21: Limited | H21: Not Linked | I21: Yes | J21: Yes
B22: BP | C22: 49 | D22: N/A | E22: Yes | F22: None | H22: Linked | I22: Yes | J22: No
B23: British American Tobacco | C23: 104 | D23: A | E23: No | F23: None | H23: Linked | I23: Yes | J23: No
B24: British Land | C24: 27 | D24: N/A | E24: N/A | F24: None | H24: Partially Linked | I24: Yes | J24: Yes
B25: BT Group | C25: 23 | D25: A | E25: Yes | F25: Reasonable | H25: Partially Linked | I25: Yes | J25: Yes
B26: Bunzl | C26: 26 | D26: N/A | E26: No | F26: Limited | H26: Not Linked | I26: Yes | J26: No
B27: Burberry Group | C27: 28 | D27: A- | E27: N/A | F27: None | H27: Linked | I27: Yes | J27: Yes
B28: Centrica | C28: 46 | D28: B | E28: Yes | F28: Limited | H28: Partially Linked | I28: Yes | J28: Yes
B29: Coca-Cola HBC | C29: 14 | D29: A | E29: Yes | F29: Limited | H29: Partially Linked | I29: Yes | J29: No
B30: Compass Group | C30: 42 | D30: N/A | E30: No | F30: Limited | H30: Partially Linked | I30: Yes | J30: Yes
B31: Convatec Group | C31: N/A | D31: B | E31: N/A | F31: Limited | H31: Partially Linked | I31: Yes | J31: No
B32: Croda International | C32: 25 | D32: A- | E32: No | F32: Limited | H32: Partially Linked | I32: Yes | J32: Yes
B33: DCC plc | C33: 41 | D33: A | E33: No | F33: Limited | H33: Not Linked | I33: Yes | J33: No
B34: Diageo | C34: 71 | D34: N/A | E34: Yes | F34: Limited | H34: Linked | I34: Yes | J34: No
B35: Diploma | C35: 4 | D35: C | E35: N/A | F35: None | H35: Not Linked | I35: Yes | J35: Yes
B36: Endeavour Mining | C36: 98 | D36: B | E36: No | F36: Limited | H36: Not Linked | I36: Yes | J36: Yes
B37: Entain | C37: 42 | D37: B | E37: N/A | F37: Limited | H37: Partially Linked | I37: Yes | J37: Yes
B38: EasyJet | C38: 5 | D38: N/A | E38: Yes | F38: Reasonable | H38: Partially Linked | I38: Yes | J38: No
B39: Experian | C39: 28 | D39: A- | E39: N/A | F39: Limited | H39: Linked | I39: Yes | J39: No
B40: F&C Investment Trust | C40: N/A | D40: N/A | E40: N/A | F40: None | H40: Partially Linked | I40: Yes | J40: No
B41: Fresnillo | C41: 2 | D41: C | E41: N/A | F41: Limited | H41: Not Linked | I41: Yes | J41: No
B42: Games Workshop | C42: 1 | D42: N/A | E42: N/A | F42: None | H42: Partially Linked | I42: Yes | J42: No
B43: Glencore | C43: 70 | D43: N/A | E43: Yes | F43: Limited | H43: Partially Linked | I43: Yes | J43: No
B44: GSK | C44: 54 | D44: A | E44: Yes | F44: Limited | H44: Linked | I44: Yes | J44: No
B45: Haleon | C45: 76 | D45: B | E45: Yes | F45: Limited | H45: Linked | I45: Yes | J45: Yes
B46: Halma | C46: 33 | D46: B | E46: N/A | F46: Limited | H46: Partially Linked | I46: Yes | J46: Yes
B47: Hargreaves Lansdown | C47: 1 | D47: N/A | E47: N/A | F47: None | H47: Partially Linked | I47: Yes | J47: No
B48: Hikma Pharmaceuticals | C48: 53 | D48: B | E48: N/A | F48: Limited | H48: Not Linked | I48: Yes | J48: No
B49: Hiscox | C49: 1 | D49: B | E49: N/A | F49: None | H49: Linked | I49: Yes | J49: Yes
B50: Howden Joinery Group | C50: 10 | D50: B | E50: N/A | F50: None | H50: Not Linked | I50: Yes | J50: No
B51: HSBC Holdings | C51: 31 | D51: N/A | E51: Yes | F51: Limited | H51: Partially Linked | I51: Yes | J51: No
B52: IMI plc | C52: 1 | D52: B | E52: N/A | F52: None | H52: Not Linked | I52: Yes | J52: Yes
... B58: International Cons. Airlines (IAG) | C58: 80 | D58: N/A | E58: N/A | F58: None | H58: Partially Linked | I58: Yes | J58: No
B59: JD Sports Fashion | C59: 1 | D59: A | E59: No | H59: Not Linked | I59: Yes | J59: Yes
B60: Kingfisher | C60: 49 | D60: A | E60: Yes | H60: Partially Linked | I60: Yes | J60: Yes
B61: Land Securities | C61: 58 | D61: N/A | E61: N/A | F61: Limited | H61: Linked | I61: Yes | J61: Yes
B62: Legal & General | C62: 73 | D62: A | E62: N/A | F62: None | H62: Linked | I62: Yes | J62: Yes
B63: Lloyds Banking Group | C63: 145 | D63: A- | E63: Yes | F63: Limited | H63: Linked | I63: Yes | J63: Yes
B64: LondonMetric Property | C64: 40 | D64: A- | E64: N/A | F64: Limited | H64: Partially Linked | I64: Yes | J64: Yes
B65: London Stock Exchange Group | C65: 59 | D65: A- | E65: Yes | F65: Limited | H65: Linked | I65: Yes | J65: Yes
B66: M&G | C66: 33 | D66: C | E66: N/A | F66: Limited | H66: Partially Linked | I66: Yes | J66: No
B67: Marks & Spencer | C67: 59 | D67: B | E67: No | F67: Limited | H67: Not Linked | I67: Yes | J67: Yes
B68: Melrose Industries | C68: 86 | D68: B | E68: Yes | F68: None | H68: Not Linked | I68: Yes | J68: Yes
B69: Mondi | C69: 109 | D69: A- | E69: Yes | F69: Limited | H69: Partially Linked | I69: Yes | J69: No
B70: National Grid | C70: 8 | D70: A- | E70: Yes | F70: Limited | H70: Linked | I70: Yes | J70: No
B71: NatWest Group | C71: 99 | D71: A | E71: N/A | F71: None | H71: Partially Linked | I71: Yes | J71: No
B72: Next plc | C72: 58 | D72: N/A | E72: N/A | F72: None | H72: Not Linked | I72: Yes | J72: No
... B104: WPP | C104: 41 | D104: B | E104: N/A | F104: Limited | H104: Linked | I104: Yes | J104: No
B106: Governance Scores
B107: Domains: | C107: G1 | H107: G2
B108: Company | C108: Sust. Report Page # | D108: CDP Score | E108: Climate KPI's | F108: Assurance Level | G108: G1 Score | H108: Diversity Linked to Exec Pay | I108: Board DEI Oversight | J108: Senior Management Target | K108: G2 Score | L108: Governance Score
B109: 3i | C109: =C5/100 -> 0.3 | D109: =IF(D5="",0,IF(D5="A",1,IF(D5="A-",0.8,IF(D5="B",0.6,IF(D5="C",0.4,IF(D5="D",0.2,IF(D5="F",0,IF(D5="N/A",0)))))))) -> 0 | E109: =IF(E5="",0,IF(E5="N/A",0,IF(E5="No",0,IF(E5="Yes",1)))) -> 0 | F109: =IF(F5="",0,IF(F5="Reasonable",1,IF(F5="Limited",0.5,IF(F5="None",0)))) -> 0.5 | G109: =(Table39[[#This Row],[Sust. Report Page '# ]]+Table39[[#This Row],[CDP Score]]+Table39[[#This Row],[Climate KPI''s]]+Table39[[#This Row],[Assurance Level]])/4 -> 0.2 | H109: =IF(H5="Not Linked",0,IF(H5="Partially Linked",0.5,IF(H5="Linked",1))) -> 1 | I109: =IF(I5="No",0,IF(I5="Yes",1)) -> 1 | J109: =IF(J5="",0,IF(J5="No",0,IF(J5="Yes",1))) -> 0 | K109: =(Table39[[#This Row],[Diversity Linked to Exec Pay]]+Table39[[#This Row],[Board DEI Oversight]]+Table39[[#This Row],[Senior Management Target]])/3 -> 0.66666667 | L109: =(Table39[[#This Row],[G1 Score]]+Table39[[#This Row],[G2 Score]])/2 -> 0.43333333
B110: Admiral Group | C110: =C6/100 -> 0.43 | D110: =IF(D6="",0,IF(D6="A",1,IF(D6="A-",0.8,IF(D6="B",0.6,IF(D6="C",0.4,IF(D6="D",0.2,IF(D6="F",0,IF(D6="N/A",0)))))))) -> 0.6 | E110: =IF(E6="",0,IF(E6="N/A",0,IF(E6="No",0,IF(E6="Yes",1)))) -> 0 | F110: =IF(F6="",0,IF(F6="Reasonable",1,IF(F6="Limited",0.5,IF(F6="None",0)))) -> 0.5 | G110: =(Table39[[#This Row],[Sust. Report Page '# ]]+Table39[[#This Row],[CDP Score]]+Table39[[#This Row],[Climate KPI''s]]+Table39[[#This Row],[Assurance Level]])/4 -> 0.3825 | H110: =IF(H6="Not Linked",0,IF(H6="Partially Linked",0.5,IF(H6="Linked",1))) -> 0.5 | I110: =IF(I6="No",0,IF(I6="Yes",1)) -> 1 | J110: =IF(J6="",0,IF(J6="No",0,IF(J6="Yes",1))) -> 1 | K110: =(Table39[[#This Row],[Diversity Linked to Exec Pay]]+Table39[[#This Row],[Board DEI Oversight]]+Table39[[#This Row],[Senior Management Target]])/3 -> 0.83333333 | L110: =(Table39[[#This Row],[G1 Score]]+Table39[[#This Row],[G2 Score]])/2 -> 0.60791667
B111: Airtel Africa | C111: =C7/100 -> 0.5 | D111: =IF(D7="",0,IF(D7="A",1,IF(D7="A-",0.8,IF(D7="B",0.6,IF(D7="C",0.4,IF(D7="D",0.2,IF(D7="F",0,IF(D7="N/A",0)))))))) -> 0 | E111: =IF(E7="",0,IF(E7="N/A",0,IF(E7="No",0,IF(E7="Yes",1)))) -> 0 | F111: =IF(F7="",0,IF(F7="Reasonable",1,IF(F7="Limited",0.5,IF(F7="None",0)))) -> 0 | G111: =(Table39[[#This Row],[Sust. Report Page '# ]]+Table39[[#This Row],[CDP Score]]+Table39[[#This Row],[Climate KPI''s]]+Table39[[#This Row],[Assurance Level]])/4 -> 0.125 | H111: =IF(H7="Not Linked",0,IF(H7="Partially Linked",0.5,IF(H7="Linked",1))) -> 0 | I111: =IF(I7="No",0,IF(I7="Yes",1)) -> 1 | J111: =IF(J7="",0,IF(J7="No",0,IF(J7="Yes",1))) -> 0 | K111: =(Table39[[#This Row],[Diversity Linked to Exec Pay]]+Table39[[#This Row],[Board DEI Oversight]]+Table39[[#This Row],[Senior Management Target]])/3 -> 0.33333333 | L111: =(Table39[[#This Row],[G1 Score]]+Table39[[#This Row],[G2 Score]])/2 -> 0.22916667
B112: Alliance Witan | C112: =C8/100 -> 0.04 | D112: =IF(D8="",0,IF(D8="A",1,IF(D8="A-",0.8,IF(D8="B",0.6,IF(D8="C",0.4,IF(D8="D",0.2,IF(D8="F",0,IF(D8="N/A",0)))))))) -> 0 | E112: =IF(E8="",0,IF(E8="N/A",0,IF(E8="No",0,IF(E8="Yes",1)))) -> 0 | F112: =IF(F8="",0,IF(F8="Reasonable",1,IF(F8="Limited",0.5,IF(F8="None",0)))) -> 0 | G112: =(Table39[[#This Row],[Sust. Report Page '# ]]+Table39[[#This Row],[CDP Score]]+Table39[[#This Row],[Climate KPI''s]]+Table39[[#This Row],[Assurance Level]])/4 -> 0.01 | H112: =IF(H8="Not Linked",0,IF(H8="Partially Linked",0.5,IF(H8="Linked",1))) -> 0.5 | I112: =IF(I8="No",0,IF(I8="Yes",1)) -> 1 | J112: =IF(J8="",0,IF(J8="No",0,IF(J8="Yes",1))) -> 0 | K112: =(Table39[[#This Row],[Diversity Linked to Exec Pay]]+Table39[[#This Row],[Board DEI Oversight]]+Table39[[#This Row],[Senior Management Target]])/3 -> 0.5 | L112: =(Table39[[#This Row],[G1 Score]]+Table39[[#This Row],[G2 Score]])/2 -> 0.255
B113: Anglo American | C113: =C9/100 -> 1.44 | D113: =IF(D9="",0,IF(D9="A",1,IF(D9="A-",0.8,IF(D9="B",0.6,IF(D9="C",0.4,IF(D9="D",0.2,IF(D9="F",0,IF(D9="N/A",0)))))))) -> 0 | E113: =IF(E9="",0,IF(E9="N/A",0,IF(E9="No",0,IF(E9="Yes",1)))) -> 1 | F113: =IF(F9="",0,IF(F9="Reasonable",1,IF(F9="Limited",0.5,IF(F9="None",0)))) -> 1 | G113: =(Table39[[#This Row],[Sust. Report Page '# ]]+Table39[[#This Row],[CDP Score]]+Table39[[#This Row],[Climate KPI''s]]+Table39[[#This Row],[Assurance Level]])/4 -> 0.86 | H113: =IF(H9="Not Linked",0,IF(H9="Partially Linked",0.5,IF(H9="Linked",1))) -> 0.5 | I113: =IF(I9="No",0,IF(I9="Yes",1)) -> 1 | J113: =IF(J9="",0,IF(J9="No",0,IF(J9="Yes",1))) -> 0 | K113: =(Table39[[#This Row],[Diversity Linked to Exec Pay]]+Table39[[#This Row],[Board DEI Oversight]]+Table39[[#This Row],[Senior Management Target]])/3 -> 0.5 | L113: =(Table39[[#This Row],[G1 Score]]+Table39[[#This Row],[G2 Score]])/2 -> 0.68
B114: Antofagasta | C114: =C10/100 -> 0.99 | D114: =IF(D10="",0,IF(D10="A",1,IF(D10="A-",0.8,IF(D10="B",0.6,IF(D10="C",0.4,IF(D10="D",0.2,IF(D10="F",0,IF(D10="N/A",0)))))))) -> 0.6 | E114: =IF(E10="",0,IF(E10="N/A",0,IF(E10="No",0,IF(E10="Yes",1)))) -> 0 | F114: =IF(F10="",0,IF(F10="Reasonable",1,IF(F10="Limited",0.5,IF(F10="None",0)))) -> 0.5 | G114: =(Table39[[#This Row],[Sust. Report Page '# ]]+Table39[[#This Row],[CDP Score]]+Table39[[#This Row],[Climate KPI''s]]+Table39[[#This Row],[Assurance Level]])/4 -> 0.5225 | H114: =IF(H10="Not Linked",0,IF(H10="Partially Linked",0.5,IF(H10="Linked",1))) -> 0 | I114: =IF(I10="No",0,IF(I10="Yes",1)) -> 1 | J114: =IF(J10="",0,IF(J10="No",0,IF(J10="Yes",1))) -> 0 | K114: =(Table39[[#This Row],[Diversity Linked to Exec Pay]]+Table39[[#This Row],[Board DEI Oversight]]+Table39[[#This Row],[Senior Management Target]])/3 -> 0.33333333 | L114: =(Table39[[#This Row],[G1 Score]]+Table39[[#This Row],[G2 Score]])/2 -> 0.42791667
B115: Ashtead Group | C115: 0 | D115: =IF(D11="",0,IF(D11="A",1,IF(D11="A-",0.8,IF(D11="B",0.6,IF(D11="C",0.4,IF(D11="D",0.2,IF(D11="F",0,IF(D11="N/A",0)))))))) -> 0.6 | E115: =IF(E11="",0,IF(E11="N/A",0,IF(E11="No",0,IF(E11="Yes",1)))) -> 0 | F115: =IF(F11="",0,IF(F11="Reasonable",1,IF(F11="Limited",0.5,IF(F11="None",0)))) -> 0 | G115: =(Table39[[#This Row],[Sust. Report Page '# ]]+Table39[[#This Row],[CDP Score]]+Table39[[#This Row],[Climate KPI''s]]+Table39[[#This Row],[Assurance Level]])/4 -> 0.15 | H115: =IF(H11="Not Linked",0,IF(H11="Partially Linked",0.5,IF(H11="Linked",1))) -> 0.5 | I115: =IF(I11="No",0,IF(I11="Yes",1)) -> 1 | J115: =IF(J11="",0,IF(J11="No",0,IF(J11="Yes",1))) -> 0 | K115: =(Table39[[#This Row],[Diversity Linked to Exec Pay]]+Table39[[#This Row],[Board DEI Oversight]]+Table39[[#This Row],[Senior Management Target]])/3 -> 0.5 | L115: =(Table39[[#This Row],[G1 Score]]+Table39[[#This Row],[G2 Score]])/2 -> 0.325
B116: Associated British Foods | C116: =C12/100 -> 0.27 | D116: =IF(D12="",0,IF(D12="A",1,IF(D12="A-",0.8,IF(D12="B",0.6,IF(D12="C",0.4,IF(D12="D",0.2,IF(D12="F",0,IF(D12="N/A",0)))))))) -> 0.6 | E116: =IF(E12="",0,IF(E12="N/A",0,IF(E12="No",0,IF(E12="Yes",1)))) -> 1 | F116: =IF(F12="",0,IF(F12="Reasonable",1,IF(F12="Limited",0.5,IF(F12="None",0)))) -> 0.5 | G116: =(Table39[[#This Row],[Sust. Report Page '# ]]+Table39[[#This Row],[CDP Score]]+Table39[[#This Row],[Climate KPI''s]]+Table39[[#This Row],[Assurance Level]])/4 -> 0.5925 | H116: =IF(H12="Not Linked",0,IF(H12="Partially Linked",0.5,IF(H12="Linked",1))) -> 0 | I116: =IF(I12="No",0,IF(I12="Yes",1)) -> 1 | J116: =IF(J12="",0,IF(J12="No",0,IF(J12="Yes",1))) -> 0 | K116: =(Table39[[#This Row],[Diversity Linked to Exec Pay]]+Table39[[#This Row],[Board DEI Oversight]]+Table39[[#This Row],[Senior Management Target]])/3 -> 0.33333333 | L116: =(Table39[[#This Row],[G1 Score]]+Table39[[#This Row],[G2 Score]])/2 -> 0.46291667
B117: AstraZeneca | C117: =C13/100 -> 0.4 | D117: =IF(D13="",0,IF(D13="A",1,IF(D13="A-",0.8,IF(D13="B",0.6,IF(D13="C",0.4,IF(D13="D",0.2,IF(D13="F",0,IF(D13="N/A",0)))))))) -> 0 | E117: =IF(E13="",0,IF(E13="N/A",0,IF(E13="No",0,IF(E13="Yes",1)))) -> 1 | F117: =IF(F13="",0,IF(F13="Reasonable",1,IF(F13="Limited",0.5,IF(F13="None",0)))) -> 0.5 | G117: =(Table39[[#This Row],[Sust. Report Page '# ]]+Table39[[#This Row],[CDP Score]]+Table39[[#This Row],[Climate KPI''s]]+Table39[[#This Row],[Assurance Level]])/4 -> 0.475 | H117: =IF(H13="Not Linked",0,IF(H13="Partially Linked",0.5,IF(H13="Linked",1))) -> 1 | I117: =IF(I13="No",0,IF(I13="Yes",1)) -> 1 | J117: =IF(J13="",0,IF(J13="No",0,IF(J13="Yes",1))) -> 0 | K117: =(Table39[[#This Row],[Diversity Linked to Exec Pay]]+Table39[[#This Row],[Board DEI Oversight]]+Table39[[#This Row],[Senior Management Target]])/3 -> 0.66666667 | L117: =(Table39[[#This Row],[G1 Score]]+Table39[[#This Row],[G2 Score]])/2 -> 0.57083333
B118: Auto Trader Group | C118: =C14/100 -> 0.18 | D118: =IF(D14="",0,IF(D14="A",1,IF(D14="A-",0.8,IF(D14="B",0.6,IF(D14="C",0.4,IF(D14="D",0.2,IF(D14="F",0,IF(D14="N/A",0)))))))) -> 0.6 | E118: =IF(E14="",0,IF(E14="N/A",0,IF(E14="No",0,IF(E14="Yes",1)))) -> 0 | F118: =IF(F14="",0,IF(F14="Reasonable",1,IF(F14="Limited",0.5,IF(F14="None",0)))) -> 0.5 | G118: =(Table39[[#This Row],[Sust. Report Page '# ]]+Table39[[#This Row],[CDP Score]]+Table39[[#This Row],[Climate KPI''s]]+Table39[[#This Row],[Assurance Level]])/4 -> 0.32 | H118: =IF(H14="Not Linked",0,IF(H14="Partially Linked",0.5,IF(H14="Linked",1))) -> 1 | I118: =IF(I14="No",0,IF(I14="Yes",1)) -> 1 | J118: =IF(J14="",0,IF(J14="No",0,IF(J14="Yes",1))) -> 1 | K118: =(Table39[[#This Row],[Diversity Linked to Exec Pay]]+Table39[[#This Row],[Board DEI Oversight]]+Table39[[#This Row],[Senior Management Target]])/3 -> 1 | L118: =(Table39[[#This Row],[G1 Score]]+Table39[[#This Row],[G2 Score]])/2 -> 0.66
B119: Aviva | C119: =C15/100 -> 0.11 | D119: =IF(D15="",0,IF(D15="A",1,IF(D15="A-",0.8,IF(D15="B",0.6,IF(D15="C",0.4,IF(D15="D",0.2,IF(D15="F",0,IF(D15="N/A",0)))))))) -> 0.8 | E119: =IF(E15="",0,IF(E15="N/A",0,IF(E15="No",0,IF(E15="Yes",1)))) -> 0 | F119: =IF(F15="",0,IF(F15="Reasonable",1,IF(F15="Limited",0.5,IF(F15="None",0)))) -> 0 | G119: =(Table39[[#This Row],[Sust. Report Page '# ]]+Table39[[#This Row],[CDP Score]]+Table39[[#This Row],[Climate KPI''s]]+Table39[[#This Row],[Assurance Level]])/4 -> 0.2275 | H119: =IF(H15="Not Linked",0,IF(H15="Partially Linked",0.5,IF(H15="Linked",1))) -> 1 | I119: =IF(I15="No",0,IF(I15="Yes",1)) -> 1 | J119: =IF(J15="",0,IF(J15="No",0,IF(J15="Yes",1))) -> 1 | K119: =(Table39[[#This Row],[Diversity Linked to Exec Pay]]+Table39[[#This Row],[Board DEI Oversight]]+Table39[[#This Row],[Senior Management Target]])/3 -> 1 | L119: =(Table39[[#This Row],[G1 Score]]+Table39[[#This Row],[G2 Score]])/2 -> 0.61375
B120: Babcock International Group | C120: =C16/100 -> 0.32 | D120: =IF(D16="",0,IF(D16="A",1,IF(D16="A-",0.8,IF(D16="B",0.6,IF(D16="C",0.4,IF(D16="D",0.2,IF(D16="F",0,IF(D16="N/A",0)))))))) -> 0 | E120: =IF(E16="",0,IF(E16="N/A",0,IF(E16="No",0,IF(E16="Yes",1)))) -> 0 | F120: =IF(F16="",0,IF(F16="Reasonable",1,IF(F16="Limited",0.5,IF(F16="None",0)))) -> 0.5 | G120: =(Table39[[#This Row],[Sust. Report Page '# ]]+Table39[[#This Row],[CDP Score]]+Table39[[#This Row],[Climate KPI''s]]+Table39[[#This Row],[Assurance Level]])/4 -> 0.205 | H120: =IF(H16="Not Linked",0,IF(H16="Partially Linked",0.5,IF(H16="Linked",1))) -> 0.5 | I120: =IF(I16="No",0,IF(I16="Yes",1)) -> 1 | J120: =IF(J16="",0,IF(J16="No",0,IF(J16="Yes",1))) -> 0 | K120: =(Table39[[#This Row],[Diversity Linked to Exec Pay]]+Table39[[#This Row],[Board DEI Oversight]]+Table39[[#This Row],[Senior Management Target]])/3 -> 0.5 | L120: =(Table39[[#This Row],[G1 Score]]+Table39[[#This Row],[G2 Score]])/2 -> 0.3525
B121: BAE Systems | C121: =C17/100 -> 0.06 | D121: =IF(D17="",0,IF(D17="A",1,IF(D17="A-",0.8,IF(D17="B",0.6,IF(D17="C",0.4,IF(D17="D",0.2,IF(D17="F",0,IF(D17="N/A",0)))))))) -> 0 | E121: =IF(E17="",0,IF(E17="N/A",0,IF(E17="No",0,IF(E17="Yes",1)))) -> 1 | F121: =IF(F17="",0,IF(F17="Reasonable",1,IF(F17="Limited",0.5,IF(F17="None",0)))) -> 0.5 | G121: =(Table39[[#This Row],[Sust. Report Page '# ]]+Table39[[#This Row],[CDP Score]]+Table39[[#This Row],[Climate KPI''s]]+Table39[[#This Row],[Assurance Level]])/4 -> 0.39 | H121: =IF(H17="Not Linked",0,IF(H17="Partially Linked",0.5,IF(H17="Linked",1))) -> 1 | I121: =IF(I17="No",0,IF(I17="Yes",1)) -> 1 | J121: =IF(J17="",0,IF(J17="No",0,IF(J17="Yes",1))) -> 0 | K121: =(Table39[[#This Row],[Diversity Linked to Exec Pay]]+Table39[[#This Row],[Board DEI Oversight]]+Table39[[#This Row],[Senior Management Target]])/3 -> 0.66666667 | L121: =(Table39[[#This Row],[G1 Score]]+Table39[[#This Row],[G2 Score]])/2 -> 0.52833333
B122: Barclays | C122: =C18/100 -> 0.41 | D122: =IF(D18="",0,IF(D18="A",1,IF(D18="A-",0.8,IF(D18="B",0.6,IF(D18="C",0.4,IF(D18="D",0.2,IF(D18="F",0,IF(D18="N/A",0)))))))) -> 0.8 | E122: =IF(E18="",0,IF(E18="N/A",0,IF(E18="No",0,IF(E18="Yes",1)))) -> 1 | F122: =IF(F18="",0,IF(F18="Reasonable",1,IF(F18="Limited",0.5,IF(F18="None",0)))) -> 0.5 | G122: =(Table39[[#This Row],[Sust. Report Page '# ]]+Table39[[#This Row],[CDP Score]]+Table39[[#This Row],[Climate KPI''s]]+Table39[[#This Row],[Assurance Level]])/4 -> 0.6775 | H122: =IF(H18="Not Linked",0,IF(H18="Partially Linked",0.5,IF(H18="Linked",1))) -> 1 | I122: =IF(I18="No",0,IF(I18="Yes",1)) -> 1 | J122: =IF(J18="",0,IF(J18="No",0,IF(J18="Yes",1))) -> 1 | K122: =(Table39[[#This Row],[Diversity Linked to Exec Pay]]+Table39[[#This Row],[Board DEI Oversight]]+Table39[[#This Row],[Senior Management Target]])/3 -> 1 | L122: =(Table39[[#This Row],[G1 Score]]+Table39[[#This Row],[G2 Score]])/2 -> 0.83875
B123: Barratt Developments | C123: 0 | D123: =IF(D19="",0,IF(D19="A",1,IF(D19="A-",0.8,IF(D19="B",0.6,IF(D19="C",0.4,IF(D19="D",0.2,IF(D19="F",0,IF(D19="N/A",0)))))))) -> 1 | E123: =IF(E19="",0,IF(E19="N/A",0,IF(E19="No",0,IF(E19="Yes",1)))) -> 0 | F123: =IF(F19="",0,IF(F19="Reasonable",1,IF(F19="Limited",0.5,IF(F19="None",0)))) -> 0.5 | G123: =(Table39[[#This Row],[Sust. Report Page '# ]]+Table39[[#This Row],[CDP Score]]+Table39[[#This Row],[Climate KPI''s]]+Table39[[#This Row],[Assurance Level]])/4 -> 0.375 | H123: =IF(H19="Not Linked",0,IF(H19="Partially Linked",0.5,IF(H19="Linked",1))) -> 0 | I123: =IF(I19="No",0,IF(I19="Yes",1)) -> 1 | J123: =IF(J19="",0,IF(J19="No",0,IF(J19="Yes",1))) -> 1 | K123: =(Table39[[#This Row],[Diversity Linked to Exec Pay]]+Table39[[#This Row],[Board DEI Oversight]]+Table39[[#This Row],[Senior Management Target]])/3 -> 0.66666667 | L123: =(Table39[[#This Row],[G1 Score]]+Table39[[#This Row],[G2 Score]])/2 -> 0.52083333
B124: Beazley | C124: =C20/100 -> 0.26 | D124: =IF(D20="",0,IF(D20="A",1,IF(D20="A-",0.8,IF(D20="B",0.6,IF(D20="C",0.4,IF(D20="D",0.2,IF(D20="F",0,IF(D20="N/A",0)))))))) -> 0 | E124: =IF(E20="",0,IF(E20="N/A",0,IF(E20="No",0,IF(E20="Yes",1)))) -> 0 | F124: =IF(F20="",0,IF(F20="Reasonable",1,IF(F20="Limited",0.5,IF(F20="None",0)))) -> 0 | G124: =(Table39[[#This Row],[Sust. Report Page '# ]]+Table39[[#This Row],[CDP Score]]+Table39[[#This Row],[Climate KPI''s]]+Table39[[#This Row],[Assurance Level]])/4 -> 0.065 | H124: =IF(H20="Not Linked",0,IF(H20="Partially Linked",0.5,IF(H20="Linked",1))) -> 1 | I124: =IF(I20="No",0,IF(I20="Yes",1)) -> 1 | J124: =IF(J20="",0,IF(J20="No",0,IF(J20="Yes",1))) -> 1 | K124: =(Table39[[#This Row],[Diversity Linked to Exec Pay]]+Table39[[#This Row],[Board DEI Oversight]]+Table39[[#This Row],[Senior Management Target]])/3 -> 1 | L124: =(Table39[[#This Row],[G1 Score]]+Table39[[#This Row],[G2 Score]])/2 -> 0.5325
B125: Berkeley Group Holdings | C125: =C21/100 -> 0.3 | D125: =IF(D21="",0,IF(D21="A",1,IF(D21="A-",0.8,IF(D21="B",0.6,IF(D21="C",0.4,IF(D21="D",0.2,IF(D21="F",0,IF(D21="N/A",0)))))))) -> 0 | E125: =IF(E21="",0,IF(E21="N/A",0,IF(E21="No",0,IF(E21="Yes",1)))) -> 0 | F125: =IF(F21="",0,IF(F21="Reasonable",1,IF(F21="Limited",0.5,IF(F21="None",0)))) -> 0.5 | G125: =(Table39[[#This Row],[Sust. Report Page '# ]]+Table39[[#This Row],[CDP Score]]+Table39[[#This Row],[Climate KPI''s]]+Table39[[#This Row],[Assurance Level]])/4 -> 0.2 | H125: =IF(H21="Not Linked",0,IF(H21="Partially Linked",0.5,IF(H21="Linked",1))) -> 0 | I125: =IF(I21="No",0,IF(I21="Yes",1)) -> 1 | J125: =IF(J21="",0,IF(J21="No",0,IF(J21="Yes",1))) -> 1 | K125: =(Table39[[#This Row],[Diversity Linked to Exec Pay]]+Table39[[#This Row],[Board DEI Oversight]]+Table39[[#This Row],[Senior Management Target]])/3 -> 0.66666667 | L125: =(Table39[[#This Row],[G1 Score]]+Table39[[#This Row],[G2 Score]])/2 -> 0.43333333
B126: BP | C126: =C22/100 -> 0.49 | D126: =IF(D22="",0,IF(D22="A",1,IF(D22="A-",0.8,IF(D22="B",0.6,IF(D22="C",0.4,IF(D22="D",0.2,IF(D22="F",0,IF(D22="N/A",0)))))))) -> 0 | E126: =IF(E22="",0,IF(E22="N/A",0,IF(E22="No",0,IF(E22="Yes",1)))) -> 1 | F126: =IF(F22="",0,IF(F22="Reasonable",1,IF(F22="Limited",0.5,IF(F22="None",0)))) -> 0 | G126: =(Table39[[#This Row],[Sust. Report Page '# ]]+Table39[[#This Row],[CDP Score]]+Table39[[#This Row],[Climate KPI''s]]+Table39[[#This Row],[Assurance Level]])/4 -> 0.3725 | H126: =IF(H22="Not Linked",0,IF(H22="Partially Linked",0.5,IF(H22="Linked",1))) -> 1 | I126: =IF(I22="No",0,IF(I22="Yes",1)) -> 1 | J126: =IF(J22="",0,IF(J22="No",0,IF(J22="Yes",1))) -> 0 | K126: =(Table39[[#This Row],[Diversity Linked to Exec Pay]]+Table39[[#This Row],[Board DEI Oversight]]+Table39[[#This Row],[Senior Management Target]])/3 -> 0.66666667 | L126: =(Table39[[#This Row],[G1 Score]]+Table39[[#This Row],[G2 Score]])/2 -> 0.51958333
B127: British American Tobacco | C127: =C23/100 -> 1.04 | D127: =IF(D23="",0,IF(D23="A",1,IF(D23="A-",0.8,IF(D23="B",0.6,IF(D23="C",0.4,IF(D23="D",0.2,IF(D23="F",0,IF(D23="N/A",0)))))))) -> 1 | E127: =IF(E23="",0,IF(E23="N/A",0,IF(E23="No",0,IF(E23="Yes",1)))) -> 0 | F127: =IF(F23="",0,IF(F23="Reasonable",1,IF(F23="Limited",0.5,IF(F23="None",0)))) -> 0 | G127: =(Table39[[#This Row],[Sust. Report Page '# ]]+Table39[[#This Row],[CDP Score]]+Table39[[#This Row],[Climate KPI''s]]+Table39[[#This Row],[Assurance Level]])/4 -> 0.51 | H127: =IF(H23="Not Linked",0,IF(H23="Partially Linked",0.5,IF(H23="Linked",1))) -> 1 | I127: =IF(I23="No",0,IF(I23="Yes",1)) -> 1 | J127: =IF(J23="",0,IF(J23="No",0,IF(J23="Yes",1))) -> 0 | K127: =(Table39[[#This Row],[Diversity Linked to Exec Pay]]+Table39[[#This Row],[Board DEI Oversight]]+Table39[[#This Row],[Senior Management Target]])/3 -> 0.66666667 | L127: =(Table39[[#This Row],[G1 Score]]+Table39[[#This Row],[G2 Score]])/2 -> 0.58833333
B128: British Land | C128: =C24/100 -> 0.27 | D128: =IF(D24="",0,IF(D24="A",1,IF(D24="A-",0.8,IF(D24="B",0.6,IF(D24="C",0.4,IF(D24="D",0.2,IF(D24="F",0,IF(D24="N/A",0)))))))) -> 0 | E128: =IF(E24="",0,IF(E24="N/A",0,IF(E24="No",0,IF(E24="Yes",1)))) -> 0 | F128: =IF(F24="",0,IF(F24="Reasonable",1,IF(F24="Limited",0.5,IF(F24="None",0)))) -> 0 | G128: =(Table39[[#This Row],[Sust. Report Page '# ]]+Table39[[#This Row],[CDP Score]]+Table39[[#This Row],[Climate KPI''s]]+Table39[[#This Row],[Assurance Level]])/4 -> 0.0675 | H128: =IF(H24="Not Linked",0,IF(H24="Partially Linked",0.5,IF(H24="Linked",1))) -> 0.5 | I128: =IF(I24="No",0,IF(I24="Yes",1)) -> 1 | J128: =IF(J24="",0,IF(J24="No",0,IF(J24="Yes",1))) -> 1 | K128: =(Table39[[#This Row],[Diversity Linked to Exec Pay]]+Table39[[#This Row],[Board DEI Oversight]]+Table39[[#This Row],[Senior Management Target]])/3 -> 0.83333333 | L128: =(Table39[[#This Row],[G1 Score]]+Table39[[#This Row],[G2 Score]])/2 -> 0.45041667
B129: BT Group | C129: =C25/100 -> 0.23 | D129: =IF(D25="",0,IF(D25="A",1,IF(D25="A-",0.8,IF(D25="B",0.6,IF(D25="C",0.4,IF(D25="D",0.2,IF(D25="F",0,IF(D25="N/A",0)))))))) -> 1 | E129: =IF(E25="",0,IF(E25="N/A",0,IF(E25="No",0,IF(E25="Yes",1)))) -> 1 | F129: =IF(F25="",0,IF(F25="Reasonable",1,IF(F25="Limited",0.5,IF(F25="None",0)))) -> 1 | G129: =(Table39[[#This Row],[Sust. Report Page '# ]]+Table39[[#This Row],[CDP Score]]+Table39[[#This Row],[Climate KPI''s]]+Table39[[#This Row],[Assurance Level]])/4 -> 0.8075 | H129: =IF(H25="Not Linked",0,IF(H25="Partially Linked",0.5,IF(H25="Linked",1))) -> 0.5 | I129: =IF(I25="No",0,IF(I25="Yes",1)) -> 1 | J129: =IF(J25="",0,IF(J25="No",0,IF(J25="Yes",1))) -> 1 | K129: =(Table39[[#This Row],[Diversity Linked to Exec Pay]]+Table39[[#This Row],[Board DEI Oversight]]+Table39[[#This Row],[Senior Management Target]])/3 -> 0.83333333 | L129: =(Table39[[#This Row],[G1 Score]]+Table39[[#This Row],[G2 Score]])/2 -> 0.82041667
B130: Bunzl | C130: =C26/100 -> 0.26 | D130: =IF(D26="",0,IF(D26="A",1,IF(D26="A-",0.8,IF(D26="B",0.6,IF(D26="C",0.4,IF(D26="D",0.2,IF(D26="F",0,IF(D26="N/A",0)))))))) -> 0 | E130: =IF(E26="",0,IF(E26="N/A",0,IF(E26="No",0,IF(E26="Yes",1)))) -> 0 | F130: =IF(F26="",0,IF(F26="Reasonable",1,IF(F26="Limited",0.5,IF(F26="None",0)))) -> 0.5 | G130: =(Table39[[#This Row],[Sust. Report Page '# ]]+Table39[[#This Row],[CDP Score]]+Table39[[#This Row],[Climate KPI''s]]+Table39[[#This Row],[Assurance Level]])/4 -> 0.19 | H130: =IF(H26="Not Linked",0,IF(H26="Partially Linked",0.5,IF(H26="Linked",1))) -> 0 | I130: =IF(I26="No",0,IF(I26="Yes",1)) -> 1 | J130: =IF(J26="",0,IF(J26="No",0,IF(J26="Yes",1))) -> 0 | K130: =(Table39[[#This Row],[Diversity Linked to Exec Pay]]+Table39[[#This Row],[Board DEI Oversight]]+Table39[[#This Row],[Senior Management Target]])/3 -> 0.33333333 | L130: =(Table39[[#This Row],[G1 Score]]+Table39[[#This Row],[G2 Score]])/2 -> 0.26166667
B131: Burberry Group | C131: =C27/100 -> 0.28 | D131: =IF(D27="",0,IF(D27="A",1,IF(D27="A-",0.8,IF(D27="B",0.6,IF(D27="C",0.4,IF(D27="D",0.2,IF(D27="F",0,IF(D27="N/A",0)))))))) -> 0.8 | E131: =IF(E27="",0,IF(E27="N/A",0,IF(E27="No",0,IF(E27="Yes",1)))) -> 0 | F131: =IF(F27="",0,IF(F27="Reasonable",1,IF(F27="Limited",0.5,IF(F27="None",0)))) -> 0 | G131: =(Table39[[#This Row],[Sust. Report Page '# ]]+Table39[[#This Row],[CDP Score]]+Table39[[#This Row],[Climate KPI''s]]+Table39[[#This Row],[Assurance Level]])/4 -> 0.27 | H131: =IF(H27="Not Linked",0,IF(H27="Partially Linked",0.5,IF(H27="Linked",1))) -> 1 | I131: =IF(I27="No",0,IF(I27="Yes",1)) -> 1 | J131: =IF(J27="",0,IF(J27="No",0,IF(J27="Yes",1))) -> 1 | K131: =(Table39[[#This Row],[Diversity Linked to Exec Pay]]+Table39[[#This Row],[Board DEI Oversight]]+Table39[[#This Row],[Senior Management Target]])/3 -> 1 | L131: =(Table39[[#This Row],[G1 Score]]+Table39[[#This Row],[G2 Score]])/2 -> 0.635
B132: Centrica | C132: =C28/100 -> 0.46 | D132: =IF(D28="",0,IF(D28="A",1,IF(D28="A-",0.8,IF(D28="B",0.6,IF(D28="C",0.4,IF(D28="D",0.2,IF(D28="F",0,IF(D28="N/A",0)))))))) -> 0.6 | E132: =IF(E28="",0,IF(E28="N/A",0,IF(E28="No",0,IF(E28="Yes",1)))) -> 1 | F132: =IF(F28="",0,IF(F28="Reasonable",1,IF(F28="Limited",0.5,IF(F28="None",0)))) -> 0.5 | G132: =(Table39[[#This Row],[Sust. Report Page '# ]]+Table39[[#This Row],[CDP Score]]+Table39[[#This Row],[Climate KPI''s]]+Table39[[#This Row],[Assurance Level]])/4 -> 0.64 | H132: =IF(H28="Not Linked",0,IF(H28="Partially Linked",0.5,IF(H28="Linked",1))) -> 0.5 | I132: =IF(I28="No",0,IF(I28="Yes",1)) -> 1 | J132: =IF(J28="",0,IF(J28="No",0,IF(J28="Yes",1))) -> 1 | K132: =(Table39[[#This Row],[Diversity Linked to Exec Pay]]+Table39[[#This Row],[Board DEI Oversight]]+Table39[[#This Row],[Senior Management Target]])/3 -> 0.83333333 | L132: =(Table39[[#This Row],[G1 Score]]+Table39[[#This Row],[G2 Score]])/2 -> 0.73666667
B133: Coca-Cola HBC | C133: =C29/100 -> 0.14 | D133: =IF(D29="",0,IF(D29="A",1,IF(D29="A-",0.8,IF(D29="B",0.6,IF(D29="C",0.4,IF(D29="D",0.2,IF(D29="F",0,IF(D29="N/A",0)))))))) -> 1 | E133: =IF(E29="",0,IF(E29="N/A",0,IF(E29="No",0,IF(E29="Yes",1)))) -> 1 | F133: =IF(F29="",0,IF(F29="Reasonable",1,IF(F29="Limited",0.5,IF(F29="None",0)))) -> 0.5 | G133: =(Table39[[#This Row],[Sust. Report Page '# ]]+Table39[[#This Row],[CDP Score]]+Table39[[#This Row],[Climate KPI''s]]+Table39[[#This Row],[Assurance Level]])/4 -> 0.66 | H133: =IF(H29="Not Linked",0,IF(H29="Partially Linked",0.5,IF(H29="Linked",1))) -> 0.5 | I133: =IF(I29="No",0,IF(I29="Yes",1)) -> 1 | J133: =IF(J29="",0,IF(J29="No",0,IF(J29="Yes",1))) -> 0 | K133: =(Table39[[#This Row],[Diversity Linked to Exec Pay]]+Table39[[#This Row],[Board DEI Oversight]]+Table39[[#This Row],[Senior Management Target]])/3 -> 0.5 | L133: =(Table39[[#This Row],[G1 Score]]+Table39[[#This Row],[G2 Score]])/2 -> 0.58
B134: Compass Group | C134: =C30/100 -> 0.42 | D134: =IF(D30="",0,IF(D30="A",1,IF(D30="A-",0.8,IF(D30="B",0.6,IF(D30="C",0.4,IF(D30="D",0.2,IF(D30="F",0,IF(D30="N/A",0)))))))) -> 0 | E134: =IF(E30="",0,IF(E30="N/A",0,IF(E30="No",0,IF(E30="Yes",1)))) -> 0 | F134: =IF(F30="",0,IF(F30="Reasonable",1,IF(F30="Limited",0.5,IF(F30="None",0)))) -> 0.5 | G134: =(Table39[[#This Row],[Sust. Report Page '# ]]+Table39[[#This Row],[CDP Score]]+Table39[[#This Row],[Climate KPI''s]]+Table39[[#This Row],[Assurance Level]])/4 -> 0.23 | H134: =IF(H30="Not Linked",0,IF(H30="Partially Linked",0.5,IF(H30="Linked",1))) -> 0.5 | I134: =IF(I30="No",0,IF(I30="Yes",1)) -> 1 | J134: =IF(J30="",0,IF(J30="No",0,IF(J30="Yes",1))) -> 1 | K134: =(Table39[[#This Row],[Diversity Linked to Exec Pay]]+Table39[[#This Row],[Board DEI Oversight]]+Table39[[#This Row],[Senior Management Target]])/3 -> 0.83333333 | L134: =(Table39[[#This Row],[G1 Score]]+Table39[[#This Row],[G2 Score]])/2 -> 0.53166667
B135: Convatec Group | C135: 0 | D135: =IF(D31="",0,IF(D31="A",1,IF(D31="A-",0.8,IF(D31="B",0.6,IF(D31="C",0.4,IF(D31="D",0.2,IF(D31="F",0,IF(D31="N/A",0)))))))) -> 0.6 | E135: =IF(E31="",0,IF(E31="N/A",0,IF(E31="No",0,IF(E31="Yes",1)))) -> 0 | F135: =IF(F31="",0,IF(F31="Reasonable",1,IF(F31="Limited",0.5,IF(F31="None",0)))) -> 0.5 | G135: =(Table39[[#This Row],[Sust. Report Page '# ]]+Table39[[#This Row],[CDP Score]]+Table39[[#This Row],[Climate KPI''s]]+Table39[[#This Row],[Assurance Level]])/4 -> 0.275 | H135: =IF(H31="Not Linked",0,IF(H31="Partially Linked",0.5,IF(H31="Linked",1))) -> 0.5 | I135: =IF(I31="No",0,IF(I31="Yes",1)) -> 1 | J135: =IF(J31="",0,IF(J31="No",0,IF(J31="Yes",1))) -> 0 | K135: =(Table39[[#This Row],[Diversity Linked to Exec Pay]]+Table39[[#This Row],[Board DEI Oversight]]+Table39[[#This Row],[Senior Management Target]])/3 -> 0.5 | L135: =(Table39[[#This Row],[G1 Score]]+Table39[[#This Row],[G2 Score]])/2 -> 0.3875
B136: Croda International | C136: =C32/100 -> 0.25 | D136: =IF(D32="",0,IF(D32="A",1,IF(D32="A-",0.8,IF(D32="B",0.6,IF(D32="C",0.4,IF(D32="D",0.2,IF(D32="F",0,IF(D32="N/A",0)))))))) -> 0.8 | E136: =IF(E32="",0,IF(E32="N/A",0,IF(E32="No",0,IF(E32="Yes",1)))) -> 0 | F136: =IF(F32="",0,IF(F32="Reasonable",1,IF(F32="Limited",0.5,IF(F32="None",0)))) -> 0.5 | G136: =(Table39[[#This Row],[Sust. Report Page '# ]]+Table39[[#This Row],[CDP Score]]+Table39[[#This Row],[Climate KPI''s]]+Table39[[#This Row],[Assurance Level]])/4 -> 0.3875 | H136: =IF(H32="Not Linked",0,IF(H32="Partially Linked",0.5,IF(H32="Linked",1))) -> 0.5 | I136: =IF(I32="No",0,IF(I32="Yes",1)) -> 1 | J136: =IF(J32="",0,IF(J32="No",0,IF(J32="Yes",1))) -> 1 | K136: =(Table39[[#This Row],[Diversity Linked to Exec Pay]]+Table39[[#This Row],[Board DEI Oversight]]+Table39[[#This Row],[Senior Management Target]])/3 -> 0.83333333 | L136: =(Table39[[#This Row],[G1 Score]]+Table39[[#This Row],[G2 Score]])/2 -> 0.61041667
B137: DCC plc | C137: =C33/100 -> 0.41 | D137: =IF(D33="",0,IF(D33="A",1,IF(D33="A-",0.8,IF(D33="B",0.6,IF(D33="C",0.4,IF(D33="D",0.2,IF(D33="F",0,IF(D33="N/A",0)))))))) -> 1 | E137: =IF(E33="",0,IF(E33="N/A",0,IF(E33="No",0,IF(E33="Yes",1)))) -> 0 | F137: =IF(F33="",0,IF(F33="Reasonable",1,IF(F33="Limited",0.5,IF(F33="None",0)))) -> 0.5 | G137: =(Table39[[#This Row],[Sust. Report Page '# ]]+Table39[[#This Row],[CDP Score]]+Table39[[#This Row],[Climate KPI''s]]+Table39[[#This Row],[Assurance Level]])/4 -> 0.4775 | H137: =IF(H33="Not Linked",0,IF(H33="Partially Linked",0.5,IF(H33="Linked",1))) -> 0 | I137: =IF(I33="No",0,IF(I33="Yes",1)) -> 1 | J137: =IF(J33="",0,IF(J33="No",0,IF(J33="Yes",1))) -> 0 | K137: =(Table39[[#This Row],[Diversity Linked to Exec Pay]]+Table39[[#This Row],[Board DEI Oversight]]+Table39[[#This Row],[Senior Management Target]])/3 -> 0.33333333 | L137: =(Table39[[#This Row],[G1 Score]]+Table39[[#This Row],[G2 Score]])/2 -> 0.40541667
B138: Diageo | C138: =C34/100 -> 0.71 | D138: =IF(D34="",0,IF(D34="A",1,IF(D34="A-",0.8,IF(D34="B",0.6,IF(D34="C",0.4,IF(D34="D",0.2,IF(D34="F",0,IF(D34="N/A",0)))))))) -> 0 | E138: =IF(E34="",0,IF(E34="N/A",0,IF(E34="No",0,IF(E34="Yes",1)))) -> 1 | F138: =IF(F34="",0,IF(F34="Reasonable",1,IF(F34="Limited",0.5,IF(F34="None",0)))) -> 0.5 | G138: =(Table39[[#This Row],[Sust. Report Page '# ]]+Table39[[#This Row],[CDP Score]]+Table39[[#This Row],[Climate KPI''s]]+Table39[[#This Row],[Assurance Level]])/4 -> 0.5525 | H138: =IF(H34="Not Linked",0,IF(H34="Partially Linked",0.5,IF(H34="Linked",1))) -> 1 | I138: =IF(I34="No",0,IF(I34="Yes",1)) -> 1 | J138: =IF(J34="",0,IF(J34="No",0,IF(J34="Yes",1))) -> 0 | K138: =(Table39[[#This Row],[Diversity Linked to Exec Pay]]+Table39[[#This Row],[Board DEI Oversight]]+Table39[[#This Row],[Senior Management Target]])/3 -> 0.66666667 | L138: =(Table39[[#This Row],[G1 Score]]+Table39[[#This Row],[G2 Score]])/2 -> 0.60958333
...

Sheet Methods
B2: Environment | F2: Governance Treatment
B3: E1 - Climate Targets | C3: E2 - Investment and Transition Actions | D3: E3 - Climate Reporting
F4: Governance-related indicators are treated as embedded within the live Environment and Social frameworks rather than presented as a
B5: 1. Net Zero Commitment Year | C5: 1. Decarbonisation Capex (% of total capex) | D5: 1. TCFD Disclosure Completeness | F5: standalone score. In the underlying methodology, governance appears through strategy, oversight, incentives, transparency, and
B6: Earlier = stronger commitment = higher inverted score. | C6: Score = min(1, Capex% ÷ 10%) | D6: Checklist of 11 recommended disclosures. | F6: assurance-related signals. These include ESG integration into corporate strategy and risk management, board-level oversight structures,
B7: Example scoring: | C7: So 10%+ = max score. | D7: Score = (# disclosed ÷ 11) | F7: diversity-linked incentives, formal committees, external frameworks, and third-party assurance.
B8: ≤ 2030 → 1.0
B9: 2031–2040 → 0.75 | C9: 2. Green Bonds | D9: 2. CDP Score - https://knowesg.com/ | F9: For the website, those governance signals are reflected primarily through the reporting, oversight, and incentive-related measures already
B10: 2041–2050 → 0.5 | C10: Issued > £1bn = 1 | D10: Map A/A- = 1 → B = 0.7 → C = 0.4 → D = 0.2 → F = 0 | F10: captured inside the Environment and Social domains. This keeps governance visible in the logic of the index without displaying it as a separate
B11: > 2050 / no year → 0.2 | C11: £100m–1bn = 0.5 | F11: scored pillar.
B12: No commitment → 0 | C12: <£100m = 0.25 | D12: 3. Climate KPIs in Executive Pay
C13: None = 0 | D13: Binary:
B14: 2. Scope Coverage | D14: Yes = 1
B15: Scopes 1+2+3 → 1 | C15: 3. RE100/EP100/EV100 Membership | D15: No = 0
B16: Scopes 1+2 only → 0.5 | C16: Binary:
B17: Scope 1 only → 0.25 | C17: Yes = 1 | D17: 4. Assurance Level
B18: None → 0 | C18: No = 0 | D18: Reasonable = 1
D19: Limited = 0.5
B20: 3. SBTi Validation | C20: 4. Internal Carbon Price | D20: None = 0
B21: 1.5°C → 1 | C21: Strong (£100+/tCO₂e) = 1
B22: WB2°C → 0.75 | C22: Medium (£50–100) = 0.75
B23: 2°C → 0.5 | C23: Basic (<£50) = 0.5
B24: Commit only → 0.25 | C24: Planned = 0.25
B25: No SBTi → 0 | C25: None = 0
B27: 4. TPI Alignment
B28: TPI gives 0–4 or 0–5 level scores; normalize by dividing by max.
B31: Social
B32: S1 - DEI Targets & Representation | C32: S2 - Programmes & Memberships | D32: S3 - Social Governance & Incentives
B34: 1. Gender/Ethnicity Targets | C34: 1. DEI Memberships | D34: 1. DEI KPIs in Exec Pay
B35: Use your existing classification: | C35: Binary (0 or 1) for each: | D35: Yes = 1
C36: Stonewall | D36: No = 0
B37: Formal numeric target → 1 | C37: 10,000 Black Interns
B38: Aspirational target → 0.6 | C38: Race at Work Charter | D38: 2. Board Oversight
B39: Metric only (“monitoring”) → 0.3 | C39: Any other DEI coalition | D39: Dedicated DEI/People Committee = 1
B40: No target → 0 | D40: Some oversight = 0.5
C41: Normalize by dividing by total possible memberships. | D41: None = 0
B42: 2. Representation thresholds
B43: Gender at board/exec/workforce: | C43: 2. Pay Gap Disclosures | D43: 3. Disclosure Quality
B44: ≥50% women → 1 | C44: Gender + Ethnicity = 1 | D44: Checklist; score = (# items disclosed ÷ possible items)
B45: ≥40% → 0.75 | C45: Gender only = 0.5
B46: ≥30% → 0.5 | C46: None = 0
B47: <30% → 0.25
C48: 3. Internal DEI Programmes
B49: Ethnicity representation: | C49: Exec‑level DEI officer = 1
B50: ≥15% exec = 1 | C50: ERGs, formal training programs = +0.25 each (cap at 1)
B51: ≥10% = 0.75
B52: ≥5% = 0.5
B53: <5% = 0.25
B55: 3. Target Deadline Strength
B56: 2025 or earlier → 1
B57: 2030 → 0.5
B58: No deadline → 0

Sheet Master Company List
B2: Company Name | C2: Ticker | D2: Sector | E2: Website | F2: Annual Report URL | G2: ESG/Sustainability Report URL | H2: Reporting Year
B3: 3i | C3: III | D3: Financial services | E3: 3i.com [3i.com] | F3: 3i Group plc Annual Report and Accounts 2023 [editor.3i.com] | G3: https://editor.3i.com/investor-relations/report-library/2023/sustainability-report-2023/ [editor.3i.com] | H3: 2023
B4: Admiral Group | C4: ADM | D4: Insurance | E4: admiralgroup.co.uk | F4: Admiral Annual Financial Report 2024 [admiralgroup.co.uk] | G4: https://www.admiralgroup.co.uk/sites/default/files_public/annual-report/2024_Admiral_ESG_Report.pdf [admiralgroup.co.uk] | H4: 2024
B5: Airtel Africa | C5: AAF | D5: Telecommunications services | E5: airtel.africa | F5: https://airtel.africa/assets/pdf/annual_reports/Airtel_Africa_Annual_Report_2023.pdf | G5: https://airtel.africa/assets/pdf/sustainability_reports/Airtel_Africa_Sustainability_Report_2023.pdf | H5: 2023
B6: Alliance Witan | C6: ALW | D6: Investment Trusts | E6: alliancewitan.com | F6: https://www.alliancewitan.com/media/1234/alliance-witan-annual-report-2024.pdf [alliancewitan.com] | G6: Included in Annual Report (Integrated) [alliancewitan.com] | H6: 2024
B7: Anglo American | C7: AAL | D7: Mining | E7: angloamerican.com | F7: https://www.angloamerican.com/~/media/Files/A/Anglo-American-Group/PLC/investor-presentation/annual-report-2024.pdf | G7: https://www.angloamerican.com/~/media/Files/A/Anglo-American-Group/PLC/sustainability-report-2024.pdf | H7: 2024
B8: Antofagasta | C8: ANTO | D8: Mining | E8: antofagasta.co.uk | F8: https://www.antofagasta.co.uk/~/media/Files/A/Antofagasta/reports/2024-annual-report.pdf | G8: https://www.antofagasta.co.uk/~/media/Files/A/Antofagasta/reports/2024-sustainability-report.pdf | H8: 2024
B9: Ashtead Group | C9: AHT | D9: Support services | E9: ashtead-group.com | F9: https://www.ashtead-group.com/media/xyzh1234/Ashtead_Group_Annual_Report_2025.pdf | G9: https://www.ashtead-group.com/media/xyzh1234/Ashtead_Group_Sustainability_Report_2025.pdf | H9: 2025
B10: Associated British Foods | C10: ABF | D10: Food & tobacco | E10: abf.co.uk | F10: https://www.abf.co.uk/content/dam/abf/corporate/Documents/AnnualReports/2024_annual_report.pdf | G10: https://www.abf.co.uk/content/dam/abf/corporate/Documents/Sustainability/ABF_CSR_Report_2024.pdf | H10: 2024
B11: AstraZeneca | C11: AZN | D11: Pharmaceuticals & biotechnology | E11: astrazeneca.com [en.wikipedia.org] | F11: https://www.astrazeneca.com/content/dam/az/Investor_Relations/annual-report-2024.pdf [en.wikipedia.org] | G11: https://www.astrazeneca.com/content/dam/az/Sustainability_Report_2024.pdf [en.wikipedia.org] | H11: 2024
B12: Auto Trader Group | C12: AUTO | D12: Media | E12: autotrader.co.uk [en.wikipedia.org] | F12: https://plc.autotrader.co.uk/wp-content/uploads/2023/06/AutoTrader-Annual-Report-2023.pdf | G12: https://plc.autotrader.co.uk/wp-content/uploads/2023/06/AutoTrader-ESG-Report-2023.pdf | H12: 2023
B13: Aviva | C13: AV | D13: Life insurance | E13: aviva.com | F13: https://www.aviva.com/content/dam/aviva-corporate/documents/investors/pdfs/reports/2024/aviva-annual-report-2024.pdf | G13: https://www.aviva.com/content/dam/aviva-corporate/documents/sustainability/pdfs/2024/aviva-sustainability-report-2024.pdf | H13: 2024
B14: Babcock International Group | C14: BAB | D14: Aerospace & defence | E14: babcockinternational.com | F14: https://www.babcockinternational.com/wp-content/uploads/2023/06/Babcock-International-Annual-Report-2023.pdf | G14: https://www.babcockinternational.com/wp-content/uploads/2023/07/Babcock-ESG-Report-2023.pdf | H14: 2023
... B35: Entain | C35: ENT | D35: Travel & leisure | E35: entain.com | F35: https://entaingroup.com/wp-content/uploads/2024/03/Entain-Annual-Report-2024.pdf | G35: https://entaingroup.com/wp-content/uploads/2024/03/Entain-ESG-Report-2024.pdf | H35: 2024
B36: EasyJet | C36: EZJ | D36: Comercial Airlines | E36: https://www.easyjet.com/en/
B37: Experian | C37: EXPN | D37: Support services | E37: experianplc.com | F37: https://www.experianplc.com/media/abcd1234/experian-annual-report-2024.pdf | G37: https://www.experianplc.com/media/abcd5678/experian-sustainability-report-2024.pdf | H37: 2024
B38: F&C Investment Trust | C38: FCIT | D38: Collective investments | E38: fandc.com | F38: https://www.bmogam.com/fandc-investment-trust/wp-content/uploads/2024/02/FandC-IT-Annual-Report-2023.pdf | G38: https://www.bmogam.com/fandc-investment-trust/wp-content/uploads/2024/02/FandC-IT-ESG-Report-2023.pdf | H38: 2023
B39: Fresnillo | C39: FRES | D39: Mining | E39: fresnilloplc.com | F39: https://www.fresnilloplc.com/media/abcd1234/Fresnillo-Annual-Report-2023.pdf | G39: https://www.fresnilloplc.com/media/abcd5678/Fresnillo-CSR-Report-2023.pdf | H39: 2023
B40: Games Workshop | C40: GAW | D40: Leisure Goods | E40: investor.games-workshop.com | F40: https://investor.games-workshop.com/wp-content/uploads/2023/07/Games-Workshop-Annual-Report-2023.pdf | G40: https://investor.games-workshop.com/wp-content/uploads/2023/07/Games-Workshop-ESG-Report-2023.pdf | H40: 2023
B41: Glencore | C41: GLEN | D41: Mining | E41: glencore.com | F41: https://www.glencore.com/dam/jcr:abcdef12-3456-7890-abcd-ef1234567890/Glencore_Annual_Report_2024.pdf | G41: https://www.glencore.com/dam/jcr:0987abcd-6543-21ef-ba98-7654321fedcb/Glencore_Sustainability_Report_2024.pdf | H41: 2024
B42: GSK | C42: GSK | D42: Pharmaceuticals & biotechnology | E42: gsk.com | F42: https://www.gsk.com/media/abcd1234/GSK_Annual_Report_2023.pdf | G42: https://www.gsk.com/media/abcd5678/GSK_ESG_Performance_Report_2023.pdf | H42: 2023
B43: Haleon | C43: HLN | D43: Pharmaceuticals & biotechnology | E43: haleon.com | F43: https://www.haleon.com/content/dam/haleon/corporate/documents/investors/haleon-annual-report-2023.pdf | G43: https://www.haleon.com/content/dam/haleon/corporate/documents/sustainability/haleon-sustainability-report-2023.pdf | H43: 2023
B44: Halma | C44: HLMA | D44: Electronic equipment & parts | E44: halma.com | F44: https://www.halma.com/~/media/Files/H/Halma-V2/documents/reports/halma-annual-report-2024.pdf | G44: https://www.halma.com/~/media/Files/H/Halma-V2/documents/reports/halma-sustainability-report-2024.pdf | H44: 2024
B45: Hargreaves Lansdown | C45: HL.**** | D45: Financial services | E45: hl.co.uk | F45: https://www.hl.co.uk/__data/assets/pdf_file/0010/19123434/Hargreaves-Lansdown-Annual-Report-2023.pdf | G45: https://www.hl.co.uk/__data/assets/pdf_file/0011/19123435/HL_ESG_Report_2023.pdf | H45: 2023
B46: Hikma Pharmaceuticals | C46: HIK | D46: Pharmaceuticals & biotechnology | E46: hikma.com | F46: https://www.hikma.com/media/abcd1234/Hikma_Annual_Report_2023.pdf | G46: https://www.hikma.com/media/abcd5678/Hikma_Sustainability_Report_2023.pdf | H46: 2023
B47: Hiscox | C47: HSX | D47: Non-life Insurance | E47: hiscoxgroup.com | F47: https://www.hiscoxgroup.com/sites/group/files/docs/2024-03/Hiscox_Annual_Report_2024.pdf | G47: https://www.hiscoxgroup.com/sites/group/files/docs/2024-03/Hiscox_ESG_Report_2024.pdf | H47: 2024
B48: Howden Joinery Group | C48: HWDN | D48: Homebuilding & construction supplies | E48: howdenjoinerygroup.com | F48: https://www.howdenjoinerygroupplc.com/docs/librariesprovider25/annual-reports/howdens-annual-report-2023.pdf | G48: https://www.howdenjoinerygroupplc.com/docs/librariesprovider25/esg-reports/howdens-esg-report-2023.pdf | H48: 2023
... B103: WPP | C103: WPP | D103: Media | E103: wpp.com | F103: https://www.wpp.com/-/media/project/wpp/files/investors/2024/wpp-annual-report-2024.pdf | G103: https://www.wpp.com/-/media/project/wpp/files/investors/2024/wpp-sustainability-report-2024.pdf | H103: 2024
